{
  "generatedAt": "2026-07-22T21:54:29.727Z",
  "sourceSummary": "11 个功能，24 个界面页面，11 条操作链。已读取 22 个项目项、25 个团队议题、2 条看板讨论、25 个接单任务。",
  "repositories": [
    "shichai-dev/planning",
    "shichai-dev/opc-bounty-client",
    "shichai-dev/opc-bounty-admin",
    "shichai-dev/opc-bounty-server"
  ],
  "dashboardRepository": "shichai-dev/feature-dashboard",
  "issueTaskRepositories": [
    "shichai-dev/planning",
    "shichai-dev/opc-bounty-client",
    "shichai-dev/opc-bounty-admin",
    "shichai-dev/opc-bounty-server",
    "shichai-dev/feature-dashboard"
  ],
  "metrics": {
    "implemented": 10,
    "inProgress": 1,
    "planned": 0,
    "blocked": 0,
    "needsHandoff": 5,
    "openDiscussions": 2,
    "needsAiReview": 0,
    "staleDiscussions": 1,
    "issueTasks": 25,
    "openIssueTasks": 18,
    "claimedIssueTasks": 1,
    "waitingPrIssueTasks": 0,
    "blockedIssueTasks": 0
  },
  "operationStudio": {
    "defaultPageId": "home",
    "pages": [
      {
        "id": "home",
        "title": "首页",
        "eyebrow": "拾柴平台",
        "summary": "发布需求、发布项目、查看反馈的入口页。",
        "featureId": "display-board",
        "uiSurface": "用户端首页",
        "sections": [
          {
            "title": "社区工作流",
            "description": "发布需求、验证项目、沉淀案例。",
            "variant": "hero",
            "items": [
              {
                "id": "home-publish-requirement",
                "label": "发布需求",
                "summary": "智能助手整理成合作机会卡",
                "icon": "doc",
                "featureId": "requirement-publishing",
                "stepId": "publish-requirement-start"
              },
              {
                "id": "home-publish-project",
                "label": "发布项目",
                "summary": "验证真实市场信号",
                "icon": "cube",
                "featureId": "project-publishing",
                "stepId": "publish-project-start"
              },
              {
                "id": "home-showcase",
                "label": "展示案例",
                "summary": "脱敏后建立信任",
                "icon": "case",
                "featureId": "display-board",
                "stepId": "display-open-case"
              }
            ]
          },
          {
            "title": "V0 封闭验证",
            "description": "让一人公司和个体需求方更快对齐。",
            "variant": "metrics",
            "items": [
              {
                "id": "home-v0-requirement",
                "label": "我有需求，想找人帮忙",
                "summary": "智能助手整理成合作机会",
                "featureId": "requirement-publishing",
                "stepId": "publish-requirement-start"
              },
              {
                "id": "home-v0-project",
                "label": "我有项目，想找市场反馈",
                "summary": "验证真实市场信号",
                "featureId": "project-publishing",
                "stepId": "publish-project-start"
              },
              {
                "id": "home-v0-feedback",
                "label": "我有案例，想展示合作成果",
                "summary": "脱敏审核后建立信任",
                "featureId": "display-board",
                "stepId": "display-open-case"
              }
            ]
          }
        ],
        "hotspots": [
          {
            "id": "nav-home",
            "label": "首页导航",
            "kind": "icon",
            "featureId": "display-board",
            "stepId": "open-home"
          },
          {
            "id": "nav-display",
            "label": "展示台导航",
            "kind": "icon",
            "featureId": "display-board",
            "stepId": "open-display"
          },
          {
            "id": "nav-publish",
            "label": "发布导航",
            "kind": "icon",
            "featureId": "requirement-publishing",
            "stepId": "open-publish"
          },
          {
            "id": "top-search",
            "label": "搜索图标",
            "kind": "icon",
            "featureId": "display-board",
            "stepId": "open-global-search"
          },
          {
            "id": "top-notification",
            "label": "通知图标",
            "kind": "icon",
            "featureId": "profile-workbench",
            "stepId": "open-notifications"
          }
        ]
      },
      {
        "id": "display",
        "title": "展示台",
        "eyebrow": "拾柴平台",
        "summary": "查看需求和项目反馈，按热度、偏好和标签筛选。",
        "featureId": "display-board",
        "uiSurface": "展示台",
        "sections": [
          {
            "title": "展示台筛选",
            "description": "需求 / 项目、热门 / 上升最快、搜索与标签。",
            "variant": "filters",
            "items": [
              {
                "id": "display-kind-requirement",
                "label": "需求",
                "summary": "查看可揭榜需求",
                "featureId": "display-board",
                "stepId": "display-filter-requirements"
              },
              {
                "id": "display-kind-project",
                "label": "项目",
                "summary": "查看项目反馈",
                "featureId": "display-board",
                "stepId": "display-filter-projects"
              },
              {
                "id": "display-rank-hot",
                "label": "热门",
                "summary": "按关注度排序",
                "featureId": "display-board",
                "stepId": "display-rank-hot"
              },
              {
                "id": "display-rank-rising",
                "label": "上升最快",
                "summary": "按增长趋势排序",
                "featureId": "display-board",
                "stepId": "display-rank-rising"
              }
            ]
          },
          {
            "title": "项目列表",
            "description": "点击条目进入详情页，查看次级信息和反馈。",
            "variant": "list",
            "items": [
              {
                "id": "display-item-1",
                "label": "OPC UA 节点稳定性观察台 771538-2",
                "summary": "热度 42 · 次级信息",
                "featureId": "community-detail-comments",
                "stepId": "open-posting-detail"
              },
              {
                "id": "display-item-2",
                "label": "OPC UA 节点稳定性观察台 771538-10",
                "summary": "热度 30 · 次级信息",
                "featureId": "community-detail-comments",
                "stepId": "open-posting-detail"
              }
            ]
          }
        ],
        "hotspots": [
          {
            "id": "display-refresh",
            "label": "刷新按钮",
            "kind": "icon",
            "featureId": "display-board",
            "stepId": "refresh-display"
          },
          {
            "id": "display-search",
            "label": "项目搜索框",
            "kind": "input",
            "featureId": "display-board",
            "stepId": "display-search"
          },
          {
            "id": "display-expand-row",
            "label": "次级信息展开",
            "kind": "icon",
            "featureId": "community-detail-comments",
            "stepId": "expand-secondary-info"
          }
        ]
      },
      {
        "id": "publish",
        "title": "发布",
        "eyebrow": "拾柴平台",
        "summary": "发布需求或已有项目，智能助手辅助整理成可协作的公开卡片。",
        "featureId": "requirement-publishing",
        "uiSurface": "发布需求表单",
        "sections": [
          {
            "title": "发布类型",
            "description": "选择提需求或发项目。",
            "variant": "tabs",
            "items": [
              {
                "id": "publish-mode-requirement",
                "label": "提需求",
                "summary": "描述真实痛点",
                "featureId": "requirement-publishing",
                "stepId": "publish-requirement-start"
              },
              {
                "id": "publish-mode-project",
                "label": "发项目",
                "summary": "验证市场反馈",
                "featureId": "project-publishing",
                "stepId": "publish-project-start"
              }
            ]
          },
          {
            "title": "需求整理",
            "description": "输入需求、上传材料、智能初审、回答追问、生成草稿、选择标签并发布。",
            "variant": "form",
            "items": [
              {
                "id": "publish-raw-input",
                "label": "需求描述",
                "summary": "一句话描述真实痛点",
                "featureId": "requirement-publishing",
                "stepId": "write-requirement"
              },
              {
                "id": "publish-material",
                "label": "材料包",
                "summary": "上传文件或补充材料说明",
                "featureId": "requirement-publishing",
                "stepId": "attach-materials"
              },
              {
                "id": "publish-ai-review",
                "label": "智能初审",
                "summary": "生成追问和阻塞信息",
                "featureId": "ai-requirement-assistant",
                "stepId": "run-ai-review"
              },
              {
                "id": "publish-generate-draft",
                "label": "生成草稿",
                "summary": "形成合作机会卡",
                "featureId": "ai-requirement-assistant",
                "stepId": "generate-draft"
              },
              {
                "id": "publish-final",
                "label": "发布",
                "summary": "进入展示台",
                "featureId": "requirement-publishing",
                "stepId": "publish-final"
              }
            ]
          }
        ],
        "hotspots": [
          {
            "id": "publish-clear",
            "label": "清空按钮",
            "kind": "icon",
            "featureId": "requirement-publishing",
            "stepId": "clear-draft"
          },
          {
            "id": "publish-tags",
            "label": "标签选择",
            "kind": "panel",
            "featureId": "requirement-publishing",
            "stepId": "select-tags"
          }
        ]
      },
      {
        "id": "detail",
        "title": "详情页",
        "eyebrow": "拾柴平台",
        "summary": "需求 / 项目详情、评论、支持、私聊、作品提交与社区评价。",
        "featureId": "community-detail-comments",
        "uiSurface": "发布详情面板",
        "sections": [
          {
            "title": "详情主体",
            "description": "展示目标、场景、输入输出、验收标准和状态。",
            "variant": "detail",
            "items": [
              {
                "id": "detail-brief",
                "label": "机会卡",
                "summary": "需求或项目的结构化描述",
                "featureId": "community-detail-comments",
                "stepId": "read-detail"
              },
              {
                "id": "detail-comment",
                "label": "评论",
                "summary": "楼层评论和嵌套回复",
                "featureId": "community-detail-comments",
                "stepId": "comment-on-posting"
              },
              {
                "id": "detail-support",
                "label": "火柴支持",
                "summary": "支持、加赏、曝光和支持者讨论",
                "featureId": "match-support-wallet",
                "stepId": "support-with-matches"
              },
              {
                "id": "detail-private",
                "label": "私聊",
                "summary": "从公开资料进入私聊",
                "featureId": "private-messages",
                "stepId": "start-private-thread"
              },
              {
                "id": "detail-submit-work",
                "label": "提交作品",
                "summary": "开发者提交方案或作品",
                "featureId": "profile-workbench",
                "stepId": "submit-work"
              }
            ]
          }
        ],
        "hotspots": [
          {
            "id": "detail-report",
            "label": "举报按钮",
            "kind": "icon",
            "featureId": "admin-operations",
            "stepId": "report-content"
          },
          {
            "id": "detail-reply",
            "label": "回复评论",
            "kind": "button",
            "featureId": "community-detail-comments",
            "stepId": "reply-comment"
          }
        ]
      },
      {
        "id": "profile",
        "title": "我的",
        "eyebrow": "拾柴平台",
        "summary": "我的发布、工作台、参与、通知、火柴账户和设置。",
        "featureId": "profile-workbench",
        "uiSurface": "个人页仪表盘",
        "sections": [
          {
            "title": "个人工作台",
            "description": "查看自己的发布、参与、待处理和项目管理。",
            "variant": "profile",
            "items": [
              {
                "id": "profile-drafts",
                "label": "继续整理",
                "summary": "回到未发布草稿",
                "featureId": "profile-workbench",
                "stepId": "continue-draft"
              },
              {
                "id": "profile-postings",
                "label": "我的发布",
                "summary": "需求和项目发布历史",
                "featureId": "profile-workbench",
                "stepId": "view-my-postings"
              },
              {
                "id": "profile-wallet",
                "label": "火柴账户",
                "summary": "余额、权益、消费记录",
                "featureId": "match-support-wallet",
                "stepId": "view-wallet"
              },
              {
                "id": "profile-settings",
                "label": "账号设置",
                "summary": "公开资料和联系方式",
                "featureId": "profile-workbench",
                "stepId": "open-settings"
              }
            ]
          }
        ],
        "hotspots": [
          {
            "id": "profile-export",
            "label": "导出数据",
            "kind": "button",
            "featureId": "profile-workbench",
            "stepId": "export-profile-data"
          },
          {
            "id": "profile-notifications",
            "label": "待处理通知",
            "kind": "icon",
            "featureId": "profile-workbench",
            "stepId": "open-notifications"
          }
        ]
      }
    ],
    "chains": [
      {
        "id": "chain-publish-requirement",
        "title": "发布需求操作链",
        "featureId": "requirement-publishing",
        "pageIds": [
          "home",
          "publish",
          "display",
          "detail"
        ],
        "steps": [
          {
            "id": "publish-requirement-start",
            "pageId": "home",
            "label": "从首页点击发布需求"
          },
          {
            "id": "write-requirement",
            "pageId": "publish",
            "label": "填写需求描述和材料"
          },
          {
            "id": "run-ai-review",
            "pageId": "publish",
            "label": "智能初审并提出追问"
          },
          {
            "id": "generate-draft",
            "pageId": "publish",
            "label": "生成结构化机会卡"
          },
          {
            "id": "select-tags",
            "pageId": "publish",
            "label": "选择标签和展示范围"
          },
          {
            "id": "publish-final",
            "pageId": "publish",
            "label": "发布到展示台"
          },
          {
            "id": "open-posting-detail",
            "pageId": "display",
            "label": "从展示台进入详情"
          },
          {
            "id": "comment-on-posting",
            "pageId": "detail",
            "label": "围绕详情进行评论和回复"
          }
        ]
      },
      {
        "id": "chain-publish-project",
        "title": "发布项目操作链",
        "featureId": "project-publishing",
        "pageIds": [
          "home",
          "publish",
          "display",
          "detail"
        ],
        "steps": [
          {
            "id": "publish-project-start",
            "pageId": "home",
            "label": "从首页点击发布项目"
          },
          {
            "id": "project-fill-info",
            "pageId": "publish",
            "label": "填写项目名称、阶段、链接和媒体"
          },
          {
            "id": "project-select-tags",
            "pageId": "publish",
            "label": "选择项目标签"
          },
          {
            "id": "publish-final",
            "pageId": "publish",
            "label": "发布到展示台"
          },
          {
            "id": "display-filter-projects",
            "pageId": "display",
            "label": "在项目区查看反馈"
          },
          {
            "id": "support-with-matches",
            "pageId": "detail",
            "label": "支持项目或进入支持者讨论"
          }
        ]
      },
      {
        "id": "chain-community-detail",
        "title": "详情评论与私聊操作链",
        "featureId": "community-detail-comments",
        "pageIds": [
          "display",
          "detail",
          "profile"
        ],
        "steps": [
          {
            "id": "display-search",
            "pageId": "display",
            "label": "搜索或筛选条目"
          },
          {
            "id": "open-posting-detail",
            "pageId": "display",
            "label": "进入详情页"
          },
          {
            "id": "comment-on-posting",
            "pageId": "detail",
            "label": "发表评论"
          },
          {
            "id": "reply-comment",
            "pageId": "detail",
            "label": "回复楼层评论"
          },
          {
            "id": "start-private-thread",
            "pageId": "detail",
            "label": "从用户资料发起私聊"
          }
        ]
      },
      {
        "id": "chain-wallet-support",
        "title": "火柴支持与账本操作链",
        "featureId": "match-support-wallet",
        "pageIds": [
          "detail",
          "profile"
        ],
        "steps": [
          {
            "id": "support-with-matches",
            "pageId": "detail",
            "label": "选择火柴数量并支持"
          },
          {
            "id": "open-supporter-discussion",
            "pageId": "detail",
            "label": "进入支持者讨论"
          },
          {
            "id": "view-wallet",
            "pageId": "profile",
            "label": "查看火柴账户余额和权益"
          },
          {
            "id": "filter-wallet-activity",
            "pageId": "profile",
            "label": "筛选消费记录"
          }
        ]
      }
    ]
  },
  "features": [
    {
      "id": "auth-alpha-login",
      "title": "内测账号登录",
      "summary": "邮箱、手机、QQ、微信风格的内测登录入口，以及账号密码模拟登录。",
      "status": "implemented",
      "repo": "client/server",
      "lane": "server-auth",
      "ownerAi": "human",
      "verification": "local-pass",
      "uiSurfaces": [
        {
          "name": "用户端登录面板",
          "repo": "opc-bounty-client",
          "route": "/"
        },
        {
          "name": "管理端登录外壳",
          "repo": "opc-bounty-admin",
          "route": "/"
        }
      ],
      "operationChain": [
        "用户选择登录方式",
        "服务端校验内测账号",
        "客户端保存登录令牌",
        "个人页或管理端展示可访问页面"
      ],
      "linkedIssues": [],
      "discussionPrompt": "在不破坏内测账号测试的前提下，应该优先接入哪种真实登录或验证方式？",
      "openNeeds": [],
      "discussion": {
        "issueTerm": "功能讨论：auth-alpha-login",
        "newIssueUrl": "https://github.com/shichai-dev/feature-dashboard/issues/new?title=%5B%E6%83%B3%E6%B3%95%5D%5Bauth-alpha-login%5D+%E5%86%85%E6%B5%8B%E8%B4%A6%E5%8F%B7%E7%99%BB%E5%BD%95&body=%E5%8A%9F%E8%83%BD%E7%BC%96%E5%8F%B7%3A+auth-alpha-login%0A%E5%8A%9F%E8%83%BD%3A+%E5%86%85%E6%B5%8B%E8%B4%A6%E5%8F%B7%E7%99%BB%E5%BD%95%0A%E8%AE%A8%E8%AE%BA%E7%B1%BB%E5%9E%8B%3A+idea%0A%0A%E7%9B%AE%E6%A0%87%E7%95%8C%E9%9D%A2%E9%A1%B5%E9%9D%A2%3A%0A-+%E7%94%A8%E6%88%B7%E7%AB%AF%E7%99%BB%E5%BD%95%E9%9D%A2%E6%9D%BF+%28opc-bounty-client+%2F%29%0A-+%E7%AE%A1%E7%90%86%E7%AB%AF%E7%99%BB%E5%BD%95%E5%A4%96%E5%A3%B3+%28opc-bounty-admin+%2F%29%0A%0A%E5%BB%BA%E8%AE%AE%E6%88%96%E8%AF%84%E4%BB%B7%3A%0A%0A%E5%B8%8C%E6%9C%9B%E6%99%BA%E8%83%BD%E5%8A%A9%E6%89%8B%E5%A4%84%E7%90%86%3A%0A-+%5B+%5D+%E6%B1%87%E6%80%BB%E8%BF%99%E6%9D%A1%E8%AE%A8%E8%AE%BA%0A-+%5B+%5D+%E5%88%A4%E6%96%AD%E6%98%AF%E5%90%A6%E5%BD%B1%E5%93%8D%E5%8A%9F%E8%83%BD%E7%8A%B6%E6%80%81%0A-+%5B+%5D+%E8%8B%A5%E5%B7%B2%E9%87%87%E7%BA%B3%E5%88%99%E6%8B%86%E6%88%90%E5%AE%9E%E7%8E%B0%E8%AE%AE%E9%A2%98%0A-+%5B+%5D+%E8%8B%A5%E6%9B%BF%E4%BB%A3%E6%97%A7%E8%AE%A8%E8%AE%BA%E5%88%99%E6%A0%87%E8%AE%B0%E6%97%A7%E8%AF%84%E8%AE%BA%E8%BF%87%E6%9C%9F&labels=dashboard-discussion%2Cdispatch%3Apending%2Cfeature%3Aauth-alpha-login%2Cdiscussion%3Aidea",
        "count": 0,
        "counts": {
          "open": 0,
          "needsAiReview": 0,
          "implemented": 0,
          "stale": 0,
          "blocked": 0
        },
        "latestUpdatedAt": null,
        "latestTitle": null,
        "signals": []
      }
    },
    {
      "id": "requirement-publishing",
      "title": "需求发布流程",
      "summary": "包含材料、智能初审、追问、草稿生成、标签、保存和发布的需求发布流程。",
      "status": "implemented",
      "repo": "client/server",
      "lane": "client-publish",
      "ownerAi": "codex",
      "verification": "local-pass",
      "uiSurfaces": [
        {
          "name": "发布需求表单",
          "repo": "opc-bounty-client",
          "route": "/#publish"
        },
        {
          "name": "需求草稿编辑器",
          "repo": "opc-bounty-client",
          "route": "/#publish"
        }
      ],
      "operationChain": [
        "用户提交需求想法",
        "智能助手或模拟初审返回追问",
        "用户回答追问并生成草稿",
        "用户选择标签和材料",
        "服务端发布到展示台"
      ],
      "linkedIssues": [],
      "discussionPrompt": "在加入支付或外部智能服务前，发布漏斗里的哪些状态需要更清楚？",
      "openNeeds": [],
      "discussion": {
        "issueTerm": "功能讨论：requirement-publishing",
        "newIssueUrl": "https://github.com/shichai-dev/feature-dashboard/issues/new?title=%5B%E6%83%B3%E6%B3%95%5D%5Brequirement-publishing%5D+%E9%9C%80%E6%B1%82%E5%8F%91%E5%B8%83%E6%B5%81%E7%A8%8B&body=%E5%8A%9F%E8%83%BD%E7%BC%96%E5%8F%B7%3A+requirement-publishing%0A%E5%8A%9F%E8%83%BD%3A+%E9%9C%80%E6%B1%82%E5%8F%91%E5%B8%83%E6%B5%81%E7%A8%8B%0A%E8%AE%A8%E8%AE%BA%E7%B1%BB%E5%9E%8B%3A+idea%0A%0A%E7%9B%AE%E6%A0%87%E7%95%8C%E9%9D%A2%E9%A1%B5%E9%9D%A2%3A%0A-+%E5%8F%91%E5%B8%83%E9%9C%80%E6%B1%82%E8%A1%A8%E5%8D%95+%28opc-bounty-client+%2F%23publish%29%0A-+%E9%9C%80%E6%B1%82%E8%8D%89%E7%A8%BF%E7%BC%96%E8%BE%91%E5%99%A8+%28opc-bounty-client+%2F%23publish%29%0A%0A%E5%BB%BA%E8%AE%AE%E6%88%96%E8%AF%84%E4%BB%B7%3A%0A%0A%E5%B8%8C%E6%9C%9B%E6%99%BA%E8%83%BD%E5%8A%A9%E6%89%8B%E5%A4%84%E7%90%86%3A%0A-+%5B+%5D+%E6%B1%87%E6%80%BB%E8%BF%99%E6%9D%A1%E8%AE%A8%E8%AE%BA%0A-+%5B+%5D+%E5%88%A4%E6%96%AD%E6%98%AF%E5%90%A6%E5%BD%B1%E5%93%8D%E5%8A%9F%E8%83%BD%E7%8A%B6%E6%80%81%0A-+%5B+%5D+%E8%8B%A5%E5%B7%B2%E9%87%87%E7%BA%B3%E5%88%99%E6%8B%86%E6%88%90%E5%AE%9E%E7%8E%B0%E8%AE%AE%E9%A2%98%0A-+%5B+%5D+%E8%8B%A5%E6%9B%BF%E4%BB%A3%E6%97%A7%E8%AE%A8%E8%AE%BA%E5%88%99%E6%A0%87%E8%AE%B0%E6%97%A7%E8%AF%84%E8%AE%BA%E8%BF%87%E6%9C%9F&labels=dashboard-discussion%2Cdispatch%3Apending%2Cfeature%3Arequirement-publishing%2Cdiscussion%3Aidea",
        "count": 1,
        "counts": {
          "open": 1,
          "needsAiReview": 0,
          "implemented": 0,
          "stale": 1,
          "blocked": 0
        },
        "latestUpdatedAt": "2026-06-16T01:09:44Z",
        "latestTitle": "[评价][requirement-publishing] 首页内容太杂",
        "signals": [
          {
            "id": "dashboard-2",
            "number": 2,
            "title": "[评价][requirement-publishing] 首页内容太杂",
            "url": "https://github.com/shichai-dev/feature-dashboard/issues/2",
            "state": "OPEN",
            "featureId": "requirement-publishing",
            "uiSurface": "用户端首页",
            "operationStepId": "publish-requirement-start",
            "hotspotId": "home-publish-requirement",
            "type": "evaluation",
            "lifecycle": "stale",
            "needsAiReview": false,
            "commentCount": 6,
            "labels": [
              "dashboard-discussion",
              "discussion:evaluation",
              "feature:requirement-publishing",
              "dispatch:sent"
            ],
            "dispatch": {
              "status": "sent",
              "statusLabel": "已分发",
              "targetUrl": "https://github.com/shichai-dev/opc-bounty-client/issues/2",
              "targetRepo": "shichai-dev/opc-bounty-client"
            },
            "createdAt": "2026-06-15T16:09:26Z",
            "updatedAt": "2026-06-16T01:09:44Z",
            "closedAt": null,
            "preview": "功能编号: requirement-publishing 功能: 需求发布流程 界面页面: 用户端首页 操作步骤: publish-requirement-start 热点编号: home-publish-requirement 讨论类型: evaluation 选中的界面: - 页面: 首页 - 操作点: 发布需求 - 当前行为: 智能助手整理成合作..."
          }
        ]
      }
    },
    {
      "id": "project-publishing",
      "title": "项目发布流程",
      "summary": "已有项目发布流程，包含代码仓、演示、媒体、项目阶段、标签、关注、合作和评论。",
      "status": "implemented",
      "repo": "client/server",
      "lane": "client-publish",
      "ownerAi": "codex",
      "verification": "local-pass",
      "uiSurfaces": [
        {
          "name": "发布项目表单",
          "repo": "opc-bounty-client",
          "route": "/#publish-project"
        },
        {
          "name": "项目详情面板",
          "repo": "opc-bounty-client",
          "route": "/#postings/:id"
        }
      ],
      "operationChain": [
        "用户填写项目信息",
        "服务端创建项目发布",
        "其他用户表达关注或合作意向",
        "评论和支持更新项目详情"
      ],
      "linkedIssues": [],
      "discussionPrompt": "项目版本和发布说明是否应该成为一条独立操作链？",
      "openNeeds": [],
      "discussion": {
        "issueTerm": "功能讨论：project-publishing",
        "newIssueUrl": "https://github.com/shichai-dev/feature-dashboard/issues/new?title=%5B%E6%83%B3%E6%B3%95%5D%5Bproject-publishing%5D+%E9%A1%B9%E7%9B%AE%E5%8F%91%E5%B8%83%E6%B5%81%E7%A8%8B&body=%E5%8A%9F%E8%83%BD%E7%BC%96%E5%8F%B7%3A+project-publishing%0A%E5%8A%9F%E8%83%BD%3A+%E9%A1%B9%E7%9B%AE%E5%8F%91%E5%B8%83%E6%B5%81%E7%A8%8B%0A%E8%AE%A8%E8%AE%BA%E7%B1%BB%E5%9E%8B%3A+idea%0A%0A%E7%9B%AE%E6%A0%87%E7%95%8C%E9%9D%A2%E9%A1%B5%E9%9D%A2%3A%0A-+%E5%8F%91%E5%B8%83%E9%A1%B9%E7%9B%AE%E8%A1%A8%E5%8D%95+%28opc-bounty-client+%2F%23publish-project%29%0A-+%E9%A1%B9%E7%9B%AE%E8%AF%A6%E6%83%85%E9%9D%A2%E6%9D%BF+%28opc-bounty-client+%2F%23postings%2F%3Aid%29%0A%0A%E5%BB%BA%E8%AE%AE%E6%88%96%E8%AF%84%E4%BB%B7%3A%0A%0A%E5%B8%8C%E6%9C%9B%E6%99%BA%E8%83%BD%E5%8A%A9%E6%89%8B%E5%A4%84%E7%90%86%3A%0A-+%5B+%5D+%E6%B1%87%E6%80%BB%E8%BF%99%E6%9D%A1%E8%AE%A8%E8%AE%BA%0A-+%5B+%5D+%E5%88%A4%E6%96%AD%E6%98%AF%E5%90%A6%E5%BD%B1%E5%93%8D%E5%8A%9F%E8%83%BD%E7%8A%B6%E6%80%81%0A-+%5B+%5D+%E8%8B%A5%E5%B7%B2%E9%87%87%E7%BA%B3%E5%88%99%E6%8B%86%E6%88%90%E5%AE%9E%E7%8E%B0%E8%AE%AE%E9%A2%98%0A-+%5B+%5D+%E8%8B%A5%E6%9B%BF%E4%BB%A3%E6%97%A7%E8%AE%A8%E8%AE%BA%E5%88%99%E6%A0%87%E8%AE%B0%E6%97%A7%E8%AF%84%E8%AE%BA%E8%BF%87%E6%9C%9F&labels=dashboard-discussion%2Cdispatch%3Apending%2Cfeature%3Aproject-publishing%2Cdiscussion%3Aidea",
        "count": 0,
        "counts": {
          "open": 0,
          "needsAiReview": 0,
          "implemented": 0,
          "stale": 0,
          "blocked": 0
        },
        "latestUpdatedAt": null,
        "latestTitle": null,
        "signals": []
      }
    },
    {
      "id": "display-board",
      "title": "统一展示台",
      "summary": "统一展示需求和项目，支持热门、上升最快、类型、搜索和标签筛选。",
      "status": "implemented",
      "repo": "client/server",
      "lane": "client-community",
      "ownerAi": "codex",
      "verification": "local-pass",
      "uiSurfaces": [
        {
          "name": "展示台",
          "repo": "opc-bounty-client",
          "route": "/#display"
        },
        {
          "name": "全局搜索浮层",
          "repo": "opc-bounty-client",
          "route": "/#search"
        }
      ],
      "operationChain": [
        "客户端请求展示摘要",
        "服务端返回排序和筛选结果",
        "用户搜索或筛选",
        "用户打开发布详情"
      ],
      "linkedIssues": [],
      "discussionPrompt": "哪些排序信号应该向内测用户透明展示？",
      "openNeeds": [],
      "discussion": {
        "issueTerm": "功能讨论：display-board",
        "newIssueUrl": "https://github.com/shichai-dev/feature-dashboard/issues/new?title=%5B%E6%83%B3%E6%B3%95%5D%5Bdisplay-board%5D+%E7%BB%9F%E4%B8%80%E5%B1%95%E7%A4%BA%E5%8F%B0&body=%E5%8A%9F%E8%83%BD%E7%BC%96%E5%8F%B7%3A+display-board%0A%E5%8A%9F%E8%83%BD%3A+%E7%BB%9F%E4%B8%80%E5%B1%95%E7%A4%BA%E5%8F%B0%0A%E8%AE%A8%E8%AE%BA%E7%B1%BB%E5%9E%8B%3A+idea%0A%0A%E7%9B%AE%E6%A0%87%E7%95%8C%E9%9D%A2%E9%A1%B5%E9%9D%A2%3A%0A-+%E5%B1%95%E7%A4%BA%E5%8F%B0+%28opc-bounty-client+%2F%23display%29%0A-+%E5%85%A8%E5%B1%80%E6%90%9C%E7%B4%A2%E6%B5%AE%E5%B1%82+%28opc-bounty-client+%2F%23search%29%0A%0A%E5%BB%BA%E8%AE%AE%E6%88%96%E8%AF%84%E4%BB%B7%3A%0A%0A%E5%B8%8C%E6%9C%9B%E6%99%BA%E8%83%BD%E5%8A%A9%E6%89%8B%E5%A4%84%E7%90%86%3A%0A-+%5B+%5D+%E6%B1%87%E6%80%BB%E8%BF%99%E6%9D%A1%E8%AE%A8%E8%AE%BA%0A-+%5B+%5D+%E5%88%A4%E6%96%AD%E6%98%AF%E5%90%A6%E5%BD%B1%E5%93%8D%E5%8A%9F%E8%83%BD%E7%8A%B6%E6%80%81%0A-+%5B+%5D+%E8%8B%A5%E5%B7%B2%E9%87%87%E7%BA%B3%E5%88%99%E6%8B%86%E6%88%90%E5%AE%9E%E7%8E%B0%E8%AE%AE%E9%A2%98%0A-+%5B+%5D+%E8%8B%A5%E6%9B%BF%E4%BB%A3%E6%97%A7%E8%AE%A8%E8%AE%BA%E5%88%99%E6%A0%87%E8%AE%B0%E6%97%A7%E8%AF%84%E8%AE%BA%E8%BF%87%E6%9C%9F&labels=dashboard-discussion%2Cdispatch%3Apending%2Cfeature%3Adisplay-board%2Cdiscussion%3Aidea",
        "count": 0,
        "counts": {
          "open": 0,
          "needsAiReview": 0,
          "implemented": 0,
          "stale": 0,
          "blocked": 0
        },
        "latestUpdatedAt": null,
        "latestTitle": null,
        "signals": []
      }
    },
    {
      "id": "community-detail-comments",
      "title": "发布详情、评论和参与",
      "summary": "需求和项目详情页，包含评论、嵌套讨论、用户资料入口、参与和作品提交上下文。",
      "status": "implemented",
      "repo": "client/server",
      "lane": "client-community",
      "ownerAi": "codex",
      "verification": "local-pass",
      "uiSurfaces": [
        {
          "name": "发布详情面板",
          "repo": "opc-bounty-client",
          "route": "/#postings/:id"
        },
        {
          "name": "讨论楼层",
          "repo": "opc-bounty-client",
          "route": "/#postings/:id"
        }
      ],
      "operationChain": [
        "用户打开发布内容",
        "客户端加载详情数据",
        "用户评论或回复",
        "服务端记录社区互动",
        "资料页和私聊入口变为可用"
      ],
      "linkedIssues": [],
      "discussionPrompt": "评论、作品和私聊入口是否应该在视觉上分开，减少详情页拥挤感？",
      "openNeeds": [],
      "discussion": {
        "issueTerm": "功能讨论：community-detail-comments",
        "newIssueUrl": "https://github.com/shichai-dev/feature-dashboard/issues/new?title=%5B%E6%83%B3%E6%B3%95%5D%5Bcommunity-detail-comments%5D+%E5%8F%91%E5%B8%83%E8%AF%A6%E6%83%85%E3%80%81%E8%AF%84%E8%AE%BA%E5%92%8C%E5%8F%82%E4%B8%8E&body=%E5%8A%9F%E8%83%BD%E7%BC%96%E5%8F%B7%3A+community-detail-comments%0A%E5%8A%9F%E8%83%BD%3A+%E5%8F%91%E5%B8%83%E8%AF%A6%E6%83%85%E3%80%81%E8%AF%84%E8%AE%BA%E5%92%8C%E5%8F%82%E4%B8%8E%0A%E8%AE%A8%E8%AE%BA%E7%B1%BB%E5%9E%8B%3A+idea%0A%0A%E7%9B%AE%E6%A0%87%E7%95%8C%E9%9D%A2%E9%A1%B5%E9%9D%A2%3A%0A-+%E5%8F%91%E5%B8%83%E8%AF%A6%E6%83%85%E9%9D%A2%E6%9D%BF+%28opc-bounty-client+%2F%23postings%2F%3Aid%29%0A-+%E8%AE%A8%E8%AE%BA%E6%A5%BC%E5%B1%82+%28opc-bounty-client+%2F%23postings%2F%3Aid%29%0A%0A%E5%BB%BA%E8%AE%AE%E6%88%96%E8%AF%84%E4%BB%B7%3A%0A%0A%E5%B8%8C%E6%9C%9B%E6%99%BA%E8%83%BD%E5%8A%A9%E6%89%8B%E5%A4%84%E7%90%86%3A%0A-+%5B+%5D+%E6%B1%87%E6%80%BB%E8%BF%99%E6%9D%A1%E8%AE%A8%E8%AE%BA%0A-+%5B+%5D+%E5%88%A4%E6%96%AD%E6%98%AF%E5%90%A6%E5%BD%B1%E5%93%8D%E5%8A%9F%E8%83%BD%E7%8A%B6%E6%80%81%0A-+%5B+%5D+%E8%8B%A5%E5%B7%B2%E9%87%87%E7%BA%B3%E5%88%99%E6%8B%86%E6%88%90%E5%AE%9E%E7%8E%B0%E8%AE%AE%E9%A2%98%0A-+%5B+%5D+%E8%8B%A5%E6%9B%BF%E4%BB%A3%E6%97%A7%E8%AE%A8%E8%AE%BA%E5%88%99%E6%A0%87%E8%AE%B0%E6%97%A7%E8%AF%84%E8%AE%BA%E8%BF%87%E6%9C%9F&labels=dashboard-discussion%2Cdispatch%3Apending%2Cfeature%3Acommunity-detail-comments%2Cdiscussion%3Aidea",
        "count": 0,
        "counts": {
          "open": 0,
          "needsAiReview": 0,
          "implemented": 0,
          "stale": 0,
          "blocked": 0
        },
        "latestUpdatedAt": null,
        "latestTitle": null,
        "signals": []
      }
    },
    {
      "id": "private-messages",
      "title": "私聊会话",
      "summary": "私聊支持主动连续三句限制，以及通过回复解锁后续交流的模型。",
      "status": "implemented",
      "repo": "client/server",
      "lane": "client-community",
      "ownerAi": "codex",
      "verification": "local-pass",
      "uiSurfaces": [
        {
          "name": "私聊抽屉",
          "repo": "opc-bounty-client",
          "route": "/#messages"
        },
        {
          "name": "公开资料弹窗",
          "repo": "opc-bounty-client",
          "route": "/#profile/:id"
        }
      ],
      "operationChain": [
        "用户打开他人资料",
        "用户发起私聊会话",
        "服务端限制主动连续消息数量",
        "对方回复后解锁持续对话"
      ],
      "linkedIssues": [],
      "discussionPrompt": "在不公开私聊内容的前提下，管理员应该看到哪些审核证据？",
      "openNeeds": [],
      "discussion": {
        "issueTerm": "功能讨论：private-messages",
        "newIssueUrl": "https://github.com/shichai-dev/feature-dashboard/issues/new?title=%5B%E6%83%B3%E6%B3%95%5D%5Bprivate-messages%5D+%E7%A7%81%E8%81%8A%E4%BC%9A%E8%AF%9D&body=%E5%8A%9F%E8%83%BD%E7%BC%96%E5%8F%B7%3A+private-messages%0A%E5%8A%9F%E8%83%BD%3A+%E7%A7%81%E8%81%8A%E4%BC%9A%E8%AF%9D%0A%E8%AE%A8%E8%AE%BA%E7%B1%BB%E5%9E%8B%3A+idea%0A%0A%E7%9B%AE%E6%A0%87%E7%95%8C%E9%9D%A2%E9%A1%B5%E9%9D%A2%3A%0A-+%E7%A7%81%E8%81%8A%E6%8A%BD%E5%B1%89+%28opc-bounty-client+%2F%23messages%29%0A-+%E5%85%AC%E5%BC%80%E8%B5%84%E6%96%99%E5%BC%B9%E7%AA%97+%28opc-bounty-client+%2F%23profile%2F%3Aid%29%0A%0A%E5%BB%BA%E8%AE%AE%E6%88%96%E8%AF%84%E4%BB%B7%3A%0A%0A%E5%B8%8C%E6%9C%9B%E6%99%BA%E8%83%BD%E5%8A%A9%E6%89%8B%E5%A4%84%E7%90%86%3A%0A-+%5B+%5D+%E6%B1%87%E6%80%BB%E8%BF%99%E6%9D%A1%E8%AE%A8%E8%AE%BA%0A-+%5B+%5D+%E5%88%A4%E6%96%AD%E6%98%AF%E5%90%A6%E5%BD%B1%E5%93%8D%E5%8A%9F%E8%83%BD%E7%8A%B6%E6%80%81%0A-+%5B+%5D+%E8%8B%A5%E5%B7%B2%E9%87%87%E7%BA%B3%E5%88%99%E6%8B%86%E6%88%90%E5%AE%9E%E7%8E%B0%E8%AE%AE%E9%A2%98%0A-+%5B+%5D+%E8%8B%A5%E6%9B%BF%E4%BB%A3%E6%97%A7%E8%AE%A8%E8%AE%BA%E5%88%99%E6%A0%87%E8%AE%B0%E6%97%A7%E8%AF%84%E8%AE%BA%E8%BF%87%E6%9C%9F&labels=dashboard-discussion%2Cdispatch%3Apending%2Cfeature%3Aprivate-messages%2Cdiscussion%3Aidea",
        "count": 0,
        "counts": {
          "open": 0,
          "needsAiReview": 0,
          "implemented": 0,
          "stale": 0,
          "blocked": 0
        },
        "latestUpdatedAt": null,
        "latestTitle": null,
        "signals": []
      }
    },
    {
      "id": "match-support-wallet",
      "title": "火柴支持和钱包",
      "summary": "测试火柴余额、项目支持、需求加赏、会员、智能额度、曝光购买和支持者讨论组。",
      "status": "implemented",
      "repo": "client/server/admin",
      "lane": "server-wallet",
      "ownerAi": "codex",
      "verification": "local-pass",
      "uiSurfaces": [
        {
          "name": "火柴支持面板",
          "repo": "opc-bounty-client",
          "route": "/#postings/:id"
        },
        {
          "name": "个人页钱包摘要",
          "repo": "opc-bounty-client",
          "route": "/#profile"
        },
        {
          "name": "管理端火柴审计",
          "repo": "opc-bounty-admin",
          "route": "/#match-audit"
        }
      ],
      "operationChain": [
        "用户获得测试火柴",
        "用户把火柴用于支持或曝光",
        "服务端记录账本和权益",
        "客户端刷新钱包",
        "管理员审计订单或争议"
      ],
      "linkedIssues": [
        {
          "label": "服务端#1 火柴消费接口",
          "url": "https://github.com/shichai-dev/opc-bounty-server/issues/1",
          "state": "OPEN",
          "needs": "needs-db",
          "stage": "Ready",
          "verification": "none"
        },
        {
          "label": "服务端#2 火柴账本查询",
          "url": "https://github.com/shichai-dev/opc-bounty-server/issues/2",
          "state": "OPEN",
          "needs": "needs-server",
          "stage": "Ready",
          "verification": "none"
        },
        {
          "label": "用户端#1 个人页历史界面",
          "url": "https://github.com/shichai-dev/opc-bounty-client/issues/1",
          "state": "OPEN",
          "needs": "needs-api",
          "stage": "Spec",
          "verification": "none"
        },
        {
          "label": "管理端#1 审计筛选",
          "url": "https://github.com/shichai-dev/opc-bounty-admin/issues/1",
          "state": "OPEN",
          "needs": "needs-server",
          "stage": "Spec",
          "verification": "none"
        },
        {
          "label": "服务端#3 质量验证",
          "url": "https://github.com/shichai-dev/opc-bounty-server/issues/3",
          "state": "OPEN",
          "needs": "needs-review",
          "stage": "Ready",
          "verification": "none"
        }
      ],
      "discussionPrompt": "下一个扩展点是消费历史：完成接口、数据库查询、用户端历史界面、管理端筛选和质量验证。",
      "openNeeds": [
        "needs-db",
        "needs-server",
        "needs-api",
        "needs-server",
        "needs-review"
      ],
      "discussion": {
        "issueTerm": "功能讨论：match-support-wallet",
        "newIssueUrl": "https://github.com/shichai-dev/feature-dashboard/issues/new?title=%5B%E6%83%B3%E6%B3%95%5D%5Bmatch-support-wallet%5D+%E7%81%AB%E6%9F%B4%E6%94%AF%E6%8C%81%E5%92%8C%E9%92%B1%E5%8C%85&body=%E5%8A%9F%E8%83%BD%E7%BC%96%E5%8F%B7%3A+match-support-wallet%0A%E5%8A%9F%E8%83%BD%3A+%E7%81%AB%E6%9F%B4%E6%94%AF%E6%8C%81%E5%92%8C%E9%92%B1%E5%8C%85%0A%E8%AE%A8%E8%AE%BA%E7%B1%BB%E5%9E%8B%3A+idea%0A%0A%E7%9B%AE%E6%A0%87%E7%95%8C%E9%9D%A2%E9%A1%B5%E9%9D%A2%3A%0A-+%E7%81%AB%E6%9F%B4%E6%94%AF%E6%8C%81%E9%9D%A2%E6%9D%BF+%28opc-bounty-client+%2F%23postings%2F%3Aid%29%0A-+%E4%B8%AA%E4%BA%BA%E9%A1%B5%E9%92%B1%E5%8C%85%E6%91%98%E8%A6%81+%28opc-bounty-client+%2F%23profile%29%0A-+%E7%AE%A1%E7%90%86%E7%AB%AF%E7%81%AB%E6%9F%B4%E5%AE%A1%E8%AE%A1+%28opc-bounty-admin+%2F%23match-audit%29%0A%0A%E5%BB%BA%E8%AE%AE%E6%88%96%E8%AF%84%E4%BB%B7%3A%0A%0A%E5%B8%8C%E6%9C%9B%E6%99%BA%E8%83%BD%E5%8A%A9%E6%89%8B%E5%A4%84%E7%90%86%3A%0A-+%5B+%5D+%E6%B1%87%E6%80%BB%E8%BF%99%E6%9D%A1%E8%AE%A8%E8%AE%BA%0A-+%5B+%5D+%E5%88%A4%E6%96%AD%E6%98%AF%E5%90%A6%E5%BD%B1%E5%93%8D%E5%8A%9F%E8%83%BD%E7%8A%B6%E6%80%81%0A-+%5B+%5D+%E8%8B%A5%E5%B7%B2%E9%87%87%E7%BA%B3%E5%88%99%E6%8B%86%E6%88%90%E5%AE%9E%E7%8E%B0%E8%AE%AE%E9%A2%98%0A-+%5B+%5D+%E8%8B%A5%E6%9B%BF%E4%BB%A3%E6%97%A7%E8%AE%A8%E8%AE%BA%E5%88%99%E6%A0%87%E8%AE%B0%E6%97%A7%E8%AF%84%E8%AE%BA%E8%BF%87%E6%9C%9F&labels=dashboard-discussion%2Cdispatch%3Apending%2Cfeature%3Amatch-support-wallet%2Cdiscussion%3Aidea",
        "count": 0,
        "counts": {
          "open": 0,
          "needsAiReview": 0,
          "implemented": 0,
          "stale": 0,
          "blocked": 0
        },
        "latestUpdatedAt": null,
        "latestTitle": null,
        "signals": []
      }
    },
    {
      "id": "profile-workbench",
      "title": "个人页、工作台和通知",
      "summary": "用户个人区域，包含我的发布、我的参与、待处理、通知、公开资料、设置和导出操作。",
      "status": "implemented",
      "repo": "client/server",
      "lane": "client-wallet-profile",
      "ownerAi": "codex",
      "verification": "local-pass",
      "uiSurfaces": [
        {
          "name": "个人页仪表盘",
          "repo": "opc-bounty-client",
          "route": "/#profile"
        },
        {
          "name": "设置面板",
          "repo": "opc-bounty-client",
          "route": "/#settings"
        }
      ],
      "operationChain": [
        "用户打开个人页",
        "客户端加载我的发布、参与、通知和钱包",
        "用户进入工作台或设置",
        "服务端返回当前用户范围内的数据"
      ],
      "linkedIssues": [],
      "discussionPrompt": "公开内测前，待处理任务是否应该升级为跨功能收件箱？",
      "openNeeds": [],
      "discussion": {
        "issueTerm": "功能讨论：profile-workbench",
        "newIssueUrl": "https://github.com/shichai-dev/feature-dashboard/issues/new?title=%5B%E6%83%B3%E6%B3%95%5D%5Bprofile-workbench%5D+%E4%B8%AA%E4%BA%BA%E9%A1%B5%E3%80%81%E5%B7%A5%E4%BD%9C%E5%8F%B0%E5%92%8C%E9%80%9A%E7%9F%A5&body=%E5%8A%9F%E8%83%BD%E7%BC%96%E5%8F%B7%3A+profile-workbench%0A%E5%8A%9F%E8%83%BD%3A+%E4%B8%AA%E4%BA%BA%E9%A1%B5%E3%80%81%E5%B7%A5%E4%BD%9C%E5%8F%B0%E5%92%8C%E9%80%9A%E7%9F%A5%0A%E8%AE%A8%E8%AE%BA%E7%B1%BB%E5%9E%8B%3A+idea%0A%0A%E7%9B%AE%E6%A0%87%E7%95%8C%E9%9D%A2%E9%A1%B5%E9%9D%A2%3A%0A-+%E4%B8%AA%E4%BA%BA%E9%A1%B5%E4%BB%AA%E8%A1%A8%E7%9B%98+%28opc-bounty-client+%2F%23profile%29%0A-+%E8%AE%BE%E7%BD%AE%E9%9D%A2%E6%9D%BF+%28opc-bounty-client+%2F%23settings%29%0A%0A%E5%BB%BA%E8%AE%AE%E6%88%96%E8%AF%84%E4%BB%B7%3A%0A%0A%E5%B8%8C%E6%9C%9B%E6%99%BA%E8%83%BD%E5%8A%A9%E6%89%8B%E5%A4%84%E7%90%86%3A%0A-+%5B+%5D+%E6%B1%87%E6%80%BB%E8%BF%99%E6%9D%A1%E8%AE%A8%E8%AE%BA%0A-+%5B+%5D+%E5%88%A4%E6%96%AD%E6%98%AF%E5%90%A6%E5%BD%B1%E5%93%8D%E5%8A%9F%E8%83%BD%E7%8A%B6%E6%80%81%0A-+%5B+%5D+%E8%8B%A5%E5%B7%B2%E9%87%87%E7%BA%B3%E5%88%99%E6%8B%86%E6%88%90%E5%AE%9E%E7%8E%B0%E8%AE%AE%E9%A2%98%0A-+%5B+%5D+%E8%8B%A5%E6%9B%BF%E4%BB%A3%E6%97%A7%E8%AE%A8%E8%AE%BA%E5%88%99%E6%A0%87%E8%AE%B0%E6%97%A7%E8%AF%84%E8%AE%BA%E8%BF%87%E6%9C%9F&labels=dashboard-discussion%2Cdispatch%3Apending%2Cfeature%3Aprofile-workbench%2Cdiscussion%3Aidea",
        "count": 0,
        "counts": {
          "open": 0,
          "needsAiReview": 0,
          "implemented": 0,
          "stale": 0,
          "blocked": 0
        },
        "latestUpdatedAt": null,
        "latestTitle": null,
        "signals": []
      }
    },
    {
      "id": "admin-operations",
      "title": "内测管理端运营",
      "summary": "管理端仪表盘、用户、发布内容、智能服务使用、火柴支持、内容审核、文件审核和生产就绪页面。",
      "status": "implemented",
      "repo": "admin/server",
      "lane": "admin-ops",
      "ownerAi": "codex",
      "verification": "local-pass",
      "uiSurfaces": [
        {
          "name": "管理端仪表盘",
          "repo": "opc-bounty-admin",
          "route": "/"
        },
        {
          "name": "内容审核页",
          "repo": "opc-bounty-admin",
          "route": "/#content-review"
        },
        {
          "name": "文件审核页",
          "repo": "opc-bounty-admin",
          "route": "/#file-review"
        },
        {
          "name": "生产就绪页",
          "repo": "opc-bounty-admin",
          "route": "/#production-readiness"
        }
      ],
      "operationChain": [
        "管理员登录",
        "服务端校验管理员权限",
        "管理员审核用户、内容、文件、钱包或就绪状态",
        "服务端返回脱敏运营证据"
      ],
      "linkedIssues": [
        {
          "label": "管理端#1 火柴审计筛选",
          "url": "https://github.com/shichai-dev/opc-bounty-admin/issues/1",
          "state": "OPEN",
          "needs": "needs-server",
          "stage": "Spec",
          "verification": "none"
        }
      ],
      "discussionPrompt": "邀请更多测试用户前，哪些管理端决策必须有审计日志证据？",
      "openNeeds": [
        "needs-server"
      ],
      "discussion": {
        "issueTerm": "功能讨论：admin-operations",
        "newIssueUrl": "https://github.com/shichai-dev/feature-dashboard/issues/new?title=%5B%E6%83%B3%E6%B3%95%5D%5Badmin-operations%5D+%E5%86%85%E6%B5%8B%E7%AE%A1%E7%90%86%E7%AB%AF%E8%BF%90%E8%90%A5&body=%E5%8A%9F%E8%83%BD%E7%BC%96%E5%8F%B7%3A+admin-operations%0A%E5%8A%9F%E8%83%BD%3A+%E5%86%85%E6%B5%8B%E7%AE%A1%E7%90%86%E7%AB%AF%E8%BF%90%E8%90%A5%0A%E8%AE%A8%E8%AE%BA%E7%B1%BB%E5%9E%8B%3A+idea%0A%0A%E7%9B%AE%E6%A0%87%E7%95%8C%E9%9D%A2%E9%A1%B5%E9%9D%A2%3A%0A-+%E7%AE%A1%E7%90%86%E7%AB%AF%E4%BB%AA%E8%A1%A8%E7%9B%98+%28opc-bounty-admin+%2F%29%0A-+%E5%86%85%E5%AE%B9%E5%AE%A1%E6%A0%B8%E9%A1%B5+%28opc-bounty-admin+%2F%23content-review%29%0A-+%E6%96%87%E4%BB%B6%E5%AE%A1%E6%A0%B8%E9%A1%B5+%28opc-bounty-admin+%2F%23file-review%29%0A-+%E7%94%9F%E4%BA%A7%E5%B0%B1%E7%BB%AA%E9%A1%B5+%28opc-bounty-admin+%2F%23production-readiness%29%0A%0A%E5%BB%BA%E8%AE%AE%E6%88%96%E8%AF%84%E4%BB%B7%3A%0A%0A%E5%B8%8C%E6%9C%9B%E6%99%BA%E8%83%BD%E5%8A%A9%E6%89%8B%E5%A4%84%E7%90%86%3A%0A-+%5B+%5D+%E6%B1%87%E6%80%BB%E8%BF%99%E6%9D%A1%E8%AE%A8%E8%AE%BA%0A-+%5B+%5D+%E5%88%A4%E6%96%AD%E6%98%AF%E5%90%A6%E5%BD%B1%E5%93%8D%E5%8A%9F%E8%83%BD%E7%8A%B6%E6%80%81%0A-+%5B+%5D+%E8%8B%A5%E5%B7%B2%E9%87%87%E7%BA%B3%E5%88%99%E6%8B%86%E6%88%90%E5%AE%9E%E7%8E%B0%E8%AE%AE%E9%A2%98%0A-+%5B+%5D+%E8%8B%A5%E6%9B%BF%E4%BB%A3%E6%97%A7%E8%AE%A8%E8%AE%BA%E5%88%99%E6%A0%87%E8%AE%B0%E6%97%A7%E8%AF%84%E8%AE%BA%E8%BF%87%E6%9C%9F&labels=dashboard-discussion%2Cdispatch%3Apending%2Cfeature%3Aadmin-operations%2Cdiscussion%3Aidea",
        "count": 0,
        "counts": {
          "open": 0,
          "needsAiReview": 0,
          "implemented": 0,
          "stale": 0,
          "blocked": 0
        },
        "latestUpdatedAt": null,
        "latestTitle": null,
        "signals": []
      }
    },
    {
      "id": "ai-requirement-assistant",
      "title": "智能需求助手",
      "summary": "模拟或真实模型需求初审、追问生成、草稿生成、标签、使用限制和生产智能服务证据。",
      "status": "implemented",
      "repo": "server",
      "lane": "server-posting",
      "ownerAi": "codex",
      "verification": "local-pass",
      "uiSurfaces": [
        {
          "name": "需求智能初审状态",
          "repo": "opc-bounty-client",
          "route": "/#publish"
        },
        {
          "name": "管理端智能服务运营",
          "repo": "opc-bounty-admin",
          "route": "/#production-readiness"
        }
      ],
      "operationChain": [
        "用户提交需求",
        "服务端运行模拟或 DeepSeek 初审",
        "服务端记录用量和限制",
        "客户端展示追问和草稿",
        "管理员查看智能服务就绪证据"
      ],
      "linkedIssues": [],
      "discussionPrompt": "从模拟智能服务切换到真实智能服务前，应该要求哪些证据？",
      "openNeeds": [],
      "discussion": {
        "issueTerm": "功能讨论：ai-requirement-assistant",
        "newIssueUrl": "https://github.com/shichai-dev/feature-dashboard/issues/new?title=%5B%E6%83%B3%E6%B3%95%5D%5Bai-requirement-assistant%5D+%E6%99%BA%E8%83%BD%E9%9C%80%E6%B1%82%E5%8A%A9%E6%89%8B&body=%E5%8A%9F%E8%83%BD%E7%BC%96%E5%8F%B7%3A+ai-requirement-assistant%0A%E5%8A%9F%E8%83%BD%3A+%E6%99%BA%E8%83%BD%E9%9C%80%E6%B1%82%E5%8A%A9%E6%89%8B%0A%E8%AE%A8%E8%AE%BA%E7%B1%BB%E5%9E%8B%3A+idea%0A%0A%E7%9B%AE%E6%A0%87%E7%95%8C%E9%9D%A2%E9%A1%B5%E9%9D%A2%3A%0A-+%E9%9C%80%E6%B1%82%E6%99%BA%E8%83%BD%E5%88%9D%E5%AE%A1%E7%8A%B6%E6%80%81+%28opc-bounty-client+%2F%23publish%29%0A-+%E7%AE%A1%E7%90%86%E7%AB%AF%E6%99%BA%E8%83%BD%E6%9C%8D%E5%8A%A1%E8%BF%90%E8%90%A5+%28opc-bounty-admin+%2F%23production-readiness%29%0A%0A%E5%BB%BA%E8%AE%AE%E6%88%96%E8%AF%84%E4%BB%B7%3A%0A%0A%E5%B8%8C%E6%9C%9B%E6%99%BA%E8%83%BD%E5%8A%A9%E6%89%8B%E5%A4%84%E7%90%86%3A%0A-+%5B+%5D+%E6%B1%87%E6%80%BB%E8%BF%99%E6%9D%A1%E8%AE%A8%E8%AE%BA%0A-+%5B+%5D+%E5%88%A4%E6%96%AD%E6%98%AF%E5%90%A6%E5%BD%B1%E5%93%8D%E5%8A%9F%E8%83%BD%E7%8A%B6%E6%80%81%0A-+%5B+%5D+%E8%8B%A5%E5%B7%B2%E9%87%87%E7%BA%B3%E5%88%99%E6%8B%86%E6%88%90%E5%AE%9E%E7%8E%B0%E8%AE%AE%E9%A2%98%0A-+%5B+%5D+%E8%8B%A5%E6%9B%BF%E4%BB%A3%E6%97%A7%E8%AE%A8%E8%AE%BA%E5%88%99%E6%A0%87%E8%AE%B0%E6%97%A7%E8%AF%84%E8%AE%BA%E8%BF%87%E6%9C%9F&labels=dashboard-discussion%2Cdispatch%3Apending%2Cfeature%3Aai-requirement-assistant%2Cdiscussion%3Aidea",
        "count": 0,
        "counts": {
          "open": 0,
          "needsAiReview": 0,
          "implemented": 0,
          "stale": 0,
          "blocked": 0
        },
        "latestUpdatedAt": null,
        "latestTitle": null,
        "signals": []
      }
    },
    {
      "id": "public-feature-dashboard",
      "title": "公开异步功能讨论看板",
      "summary": "公开看板，用于展示已实现功能、未完成工作、界面页面、操作链、协作交接、异步评论和智能待处理队列。",
      "status": "in-progress",
      "repo": "feature-dashboard/planning",
      "lane": "qa-release",
      "ownerAi": "codex",
      "verification": "none",
      "uiSurfaces": [
        {
          "name": "公开功能讨论看板",
          "repo": "feature-dashboard",
          "route": "/"
        }
      ],
      "operationChain": [
        "功能登记表映射产品能力",
        "团队成员从看板提交想法、评价和协作请求",
        "讨论内容保存为公开代码托管议题或评论",
        "采集脚本在有令牌时读取代码托管项目、私有议题、看板议题和评论",
        "生成的状态 JSON 发布到公开页面",
        "静态看板展示仿真界面、讨论信号和智能待处理队列"
      ],
      "linkedIssues": [],
      "discussionPrompt": "哪些讨论信号应该变成实现任务？哪些旧评论应该标记为过期？",
      "openNeeds": [],
      "discussion": {
        "issueTerm": "功能讨论：public-feature-dashboard",
        "newIssueUrl": "https://github.com/shichai-dev/feature-dashboard/issues/new?title=%5B%E6%83%B3%E6%B3%95%5D%5Bpublic-feature-dashboard%5D+%E5%85%AC%E5%BC%80%E5%BC%82%E6%AD%A5%E5%8A%9F%E8%83%BD%E8%AE%A8%E8%AE%BA%E7%9C%8B%E6%9D%BF&body=%E5%8A%9F%E8%83%BD%E7%BC%96%E5%8F%B7%3A+public-feature-dashboard%0A%E5%8A%9F%E8%83%BD%3A+%E5%85%AC%E5%BC%80%E5%BC%82%E6%AD%A5%E5%8A%9F%E8%83%BD%E8%AE%A8%E8%AE%BA%E7%9C%8B%E6%9D%BF%0A%E8%AE%A8%E8%AE%BA%E7%B1%BB%E5%9E%8B%3A+idea%0A%0A%E7%9B%AE%E6%A0%87%E7%95%8C%E9%9D%A2%E9%A1%B5%E9%9D%A2%3A%0A-+%E5%85%AC%E5%BC%80%E5%8A%9F%E8%83%BD%E8%AE%A8%E8%AE%BA%E7%9C%8B%E6%9D%BF+%28feature-dashboard+%2F%29%0A%0A%E5%BB%BA%E8%AE%AE%E6%88%96%E8%AF%84%E4%BB%B7%3A%0A%0A%E5%B8%8C%E6%9C%9B%E6%99%BA%E8%83%BD%E5%8A%A9%E6%89%8B%E5%A4%84%E7%90%86%3A%0A-+%5B+%5D+%E6%B1%87%E6%80%BB%E8%BF%99%E6%9D%A1%E8%AE%A8%E8%AE%BA%0A-+%5B+%5D+%E5%88%A4%E6%96%AD%E6%98%AF%E5%90%A6%E5%BD%B1%E5%93%8D%E5%8A%9F%E8%83%BD%E7%8A%B6%E6%80%81%0A-+%5B+%5D+%E8%8B%A5%E5%B7%B2%E9%87%87%E7%BA%B3%E5%88%99%E6%8B%86%E6%88%90%E5%AE%9E%E7%8E%B0%E8%AE%AE%E9%A2%98%0A-+%5B+%5D+%E8%8B%A5%E6%9B%BF%E4%BB%A3%E6%97%A7%E8%AE%A8%E8%AE%BA%E5%88%99%E6%A0%87%E8%AE%B0%E6%97%A7%E8%AF%84%E8%AE%BA%E8%BF%87%E6%9C%9F&labels=dashboard-discussion%2Cdispatch%3Apending%2Cfeature%3Apublic-feature-dashboard%2Cdiscussion%3Aidea",
        "count": 1,
        "counts": {
          "open": 1,
          "needsAiReview": 0,
          "implemented": 0,
          "stale": 0,
          "blocked": 0
        },
        "latestUpdatedAt": "2026-06-15T15:22:36Z",
        "latestTitle": "[修改请求][public-feature-dashboard] 仿真实平台界面异步讨论流程",
        "signals": [
          {
            "id": "dashboard-1",
            "number": 1,
            "title": "[修改请求][public-feature-dashboard] 仿真实平台界面异步讨论流程",
            "url": "https://github.com/shichai-dev/feature-dashboard/issues/1",
            "state": "OPEN",
            "featureId": "public-feature-dashboard",
            "uiSurface": "- 公开功能讨论看板（feature-dashboard /）",
            "operationStepId": null,
            "hotspotId": null,
            "type": "change-request",
            "lifecycle": "accepted",
            "needsAiReview": false,
            "commentCount": 1,
            "labels": [
              "dashboard-discussion",
              "discussion:change-request",
              "status:accepted",
              "feature:public-feature-dashboard"
            ],
            "dispatch": {
              "status": "untracked",
              "statusLabel": "未进入分发",
              "targetUrl": null,
              "targetRepo": null
            },
            "createdAt": "2026-06-15T12:59:40Z",
            "updatedAt": "2026-06-15T15:22:36Z",
            "closedAt": null,
            "preview": "功能编号: public-feature-dashboard 功能: 公开异步功能讨论看板 讨论类型: 修改请求 目标界面页面: - 公开功能讨论看板（feature-dashboard /） 建议或评价: 这个看板不应该只是只读状态页。团队成员需要能从看板里直接输入新功能想法、评价已经实现的功能，并在仿真实平台界面上围绕按钮、图标、页面区域和操作链进..."
          }
        ]
      }
    }
  ],
  "uiSurfaces": [
    {
      "name": "公开功能讨论看板",
      "repo": "feature-dashboard",
      "route": "/",
      "description": "用于 公开异步功能讨论看板",
      "featureCount": 1,
      "features": [
        "公开异步功能讨论看板"
      ]
    },
    {
      "name": "内容审核页",
      "repo": "opc-bounty-admin",
      "route": "/#content-review",
      "description": "用于 内测管理端运营",
      "featureCount": 1,
      "features": [
        "内测管理端运营"
      ]
    },
    {
      "name": "文件审核页",
      "repo": "opc-bounty-admin",
      "route": "/#file-review",
      "description": "用于 内测管理端运营",
      "featureCount": 1,
      "features": [
        "内测管理端运营"
      ]
    },
    {
      "name": "生产就绪页",
      "repo": "opc-bounty-admin",
      "route": "/#production-readiness",
      "description": "用于 内测管理端运营",
      "featureCount": 1,
      "features": [
        "内测管理端运营"
      ]
    },
    {
      "name": "管理端仪表盘",
      "repo": "opc-bounty-admin",
      "route": "/",
      "description": "用于 内测管理端运营",
      "featureCount": 1,
      "features": [
        "内测管理端运营"
      ]
    },
    {
      "name": "管理端智能服务运营",
      "repo": "opc-bounty-admin",
      "route": "/#production-readiness",
      "description": "用于 智能需求助手",
      "featureCount": 1,
      "features": [
        "智能需求助手"
      ]
    },
    {
      "name": "管理端火柴审计",
      "repo": "opc-bounty-admin",
      "route": "/#match-audit",
      "description": "用于 火柴支持和钱包",
      "featureCount": 1,
      "features": [
        "火柴支持和钱包"
      ]
    },
    {
      "name": "管理端登录外壳",
      "repo": "opc-bounty-admin",
      "route": "/",
      "description": "用于 内测账号登录",
      "featureCount": 1,
      "features": [
        "内测账号登录"
      ]
    },
    {
      "name": "个人页仪表盘",
      "repo": "opc-bounty-client",
      "route": "/#profile",
      "description": "用于 个人页、工作台和通知",
      "featureCount": 1,
      "features": [
        "个人页、工作台和通知"
      ]
    },
    {
      "name": "个人页钱包摘要",
      "repo": "opc-bounty-client",
      "route": "/#profile",
      "description": "用于 火柴支持和钱包",
      "featureCount": 1,
      "features": [
        "火柴支持和钱包"
      ]
    },
    {
      "name": "全局搜索浮层",
      "repo": "opc-bounty-client",
      "route": "/#search",
      "description": "用于 统一展示台",
      "featureCount": 1,
      "features": [
        "统一展示台"
      ]
    },
    {
      "name": "公开资料弹窗",
      "repo": "opc-bounty-client",
      "route": "/#profile/:id",
      "description": "用于 私聊会话",
      "featureCount": 1,
      "features": [
        "私聊会话"
      ]
    },
    {
      "name": "发布详情面板",
      "repo": "opc-bounty-client",
      "route": "/#postings/:id",
      "description": "用于 发布详情、评论和参与",
      "featureCount": 1,
      "features": [
        "发布详情、评论和参与"
      ]
    },
    {
      "name": "发布需求表单",
      "repo": "opc-bounty-client",
      "route": "/#publish",
      "description": "用于 需求发布流程",
      "featureCount": 1,
      "features": [
        "需求发布流程"
      ]
    },
    {
      "name": "发布项目表单",
      "repo": "opc-bounty-client",
      "route": "/#publish-project",
      "description": "用于 项目发布流程",
      "featureCount": 1,
      "features": [
        "项目发布流程"
      ]
    },
    {
      "name": "展示台",
      "repo": "opc-bounty-client",
      "route": "/#display",
      "description": "用于 统一展示台",
      "featureCount": 1,
      "features": [
        "统一展示台"
      ]
    },
    {
      "name": "火柴支持面板",
      "repo": "opc-bounty-client",
      "route": "/#postings/:id",
      "description": "用于 火柴支持和钱包",
      "featureCount": 1,
      "features": [
        "火柴支持和钱包"
      ]
    },
    {
      "name": "用户端登录面板",
      "repo": "opc-bounty-client",
      "route": "/",
      "description": "用于 内测账号登录",
      "featureCount": 1,
      "features": [
        "内测账号登录"
      ]
    },
    {
      "name": "私聊抽屉",
      "repo": "opc-bounty-client",
      "route": "/#messages",
      "description": "用于 私聊会话",
      "featureCount": 1,
      "features": [
        "私聊会话"
      ]
    },
    {
      "name": "讨论楼层",
      "repo": "opc-bounty-client",
      "route": "/#postings/:id",
      "description": "用于 发布详情、评论和参与",
      "featureCount": 1,
      "features": [
        "发布详情、评论和参与"
      ]
    },
    {
      "name": "设置面板",
      "repo": "opc-bounty-client",
      "route": "/#settings",
      "description": "用于 个人页、工作台和通知",
      "featureCount": 1,
      "features": [
        "个人页、工作台和通知"
      ]
    },
    {
      "name": "需求智能初审状态",
      "repo": "opc-bounty-client",
      "route": "/#publish",
      "description": "用于 智能需求助手",
      "featureCount": 1,
      "features": [
        "智能需求助手"
      ]
    },
    {
      "name": "需求草稿编辑器",
      "repo": "opc-bounty-client",
      "route": "/#publish",
      "description": "用于 需求发布流程",
      "featureCount": 1,
      "features": [
        "需求发布流程"
      ]
    },
    {
      "name": "项目详情面板",
      "repo": "opc-bounty-client",
      "route": "/#postings/:id",
      "description": "用于 项目发布流程",
      "featureCount": 1,
      "features": [
        "项目发布流程"
      ]
    }
  ],
  "operationChains": [
    {
      "id": "auth-alpha-login",
      "name": "内测账号登录",
      "description": "邮箱、手机、QQ、微信风格的内测登录入口，以及账号密码模拟登录。",
      "status": "implemented",
      "repo": "client/server",
      "lane": "server-auth",
      "steps": [
        "用户选择登录方式",
        "服务端校验内测账号",
        "客户端保存登录令牌",
        "个人页或管理端展示可访问页面"
      ]
    },
    {
      "id": "requirement-publishing",
      "name": "需求发布流程",
      "description": "包含材料、智能初审、追问、草稿生成、标签、保存和发布的需求发布流程。",
      "status": "implemented",
      "repo": "client/server",
      "lane": "client-publish",
      "steps": [
        "用户提交需求想法",
        "智能助手或模拟初审返回追问",
        "用户回答追问并生成草稿",
        "用户选择标签和材料",
        "服务端发布到展示台"
      ]
    },
    {
      "id": "project-publishing",
      "name": "项目发布流程",
      "description": "已有项目发布流程，包含代码仓、演示、媒体、项目阶段、标签、关注、合作和评论。",
      "status": "implemented",
      "repo": "client/server",
      "lane": "client-publish",
      "steps": [
        "用户填写项目信息",
        "服务端创建项目发布",
        "其他用户表达关注或合作意向",
        "评论和支持更新项目详情"
      ]
    },
    {
      "id": "display-board",
      "name": "统一展示台",
      "description": "统一展示需求和项目，支持热门、上升最快、类型、搜索和标签筛选。",
      "status": "implemented",
      "repo": "client/server",
      "lane": "client-community",
      "steps": [
        "客户端请求展示摘要",
        "服务端返回排序和筛选结果",
        "用户搜索或筛选",
        "用户打开发布详情"
      ]
    },
    {
      "id": "community-detail-comments",
      "name": "发布详情、评论和参与",
      "description": "需求和项目详情页，包含评论、嵌套讨论、用户资料入口、参与和作品提交上下文。",
      "status": "implemented",
      "repo": "client/server",
      "lane": "client-community",
      "steps": [
        "用户打开发布内容",
        "客户端加载详情数据",
        "用户评论或回复",
        "服务端记录社区互动",
        "资料页和私聊入口变为可用"
      ]
    },
    {
      "id": "private-messages",
      "name": "私聊会话",
      "description": "私聊支持主动连续三句限制，以及通过回复解锁后续交流的模型。",
      "status": "implemented",
      "repo": "client/server",
      "lane": "client-community",
      "steps": [
        "用户打开他人资料",
        "用户发起私聊会话",
        "服务端限制主动连续消息数量",
        "对方回复后解锁持续对话"
      ]
    },
    {
      "id": "match-support-wallet",
      "name": "火柴支持和钱包",
      "description": "测试火柴余额、项目支持、需求加赏、会员、智能额度、曝光购买和支持者讨论组。",
      "status": "implemented",
      "repo": "client/server/admin",
      "lane": "server-wallet",
      "steps": [
        "用户获得测试火柴",
        "用户把火柴用于支持或曝光",
        "服务端记录账本和权益",
        "客户端刷新钱包",
        "管理员审计订单或争议"
      ]
    },
    {
      "id": "profile-workbench",
      "name": "个人页、工作台和通知",
      "description": "用户个人区域，包含我的发布、我的参与、待处理、通知、公开资料、设置和导出操作。",
      "status": "implemented",
      "repo": "client/server",
      "lane": "client-wallet-profile",
      "steps": [
        "用户打开个人页",
        "客户端加载我的发布、参与、通知和钱包",
        "用户进入工作台或设置",
        "服务端返回当前用户范围内的数据"
      ]
    },
    {
      "id": "admin-operations",
      "name": "内测管理端运营",
      "description": "管理端仪表盘、用户、发布内容、智能服务使用、火柴支持、内容审核、文件审核和生产就绪页面。",
      "status": "implemented",
      "repo": "admin/server",
      "lane": "admin-ops",
      "steps": [
        "管理员登录",
        "服务端校验管理员权限",
        "管理员审核用户、内容、文件、钱包或就绪状态",
        "服务端返回脱敏运营证据"
      ]
    },
    {
      "id": "ai-requirement-assistant",
      "name": "智能需求助手",
      "description": "模拟或真实模型需求初审、追问生成、草稿生成、标签、使用限制和生产智能服务证据。",
      "status": "implemented",
      "repo": "server",
      "lane": "server-posting",
      "steps": [
        "用户提交需求",
        "服务端运行模拟或 DeepSeek 初审",
        "服务端记录用量和限制",
        "客户端展示追问和草稿",
        "管理员查看智能服务就绪证据"
      ]
    },
    {
      "id": "public-feature-dashboard",
      "name": "公开异步功能讨论看板",
      "description": "公开看板，用于展示已实现功能、未完成工作、界面页面、操作链、协作交接、异步评论和智能待处理队列。",
      "status": "in-progress",
      "repo": "feature-dashboard/planning",
      "lane": "qa-release",
      "steps": [
        "功能登记表映射产品能力",
        "团队成员从看板提交想法、评价和协作请求",
        "讨论内容保存为公开代码托管议题或评论",
        "采集脚本在有令牌时读取代码托管项目、私有议题、看板议题和评论",
        "生成的状态 JSON 发布到公开页面",
        "静态看板展示仿真界面、讨论信号和智能待处理队列"
      ]
    }
  ],
  "handoffs": [
    {
      "title": "火柴支持和钱包",
      "summary": "该功能正在等待 needs-db。",
      "needs": "needs-db",
      "lane": "server-wallet",
      "repo": "client/server/admin"
    },
    {
      "title": "火柴支持和钱包",
      "summary": "该功能正在等待 needs-server。",
      "needs": "needs-server",
      "lane": "server-wallet",
      "repo": "client/server/admin"
    },
    {
      "title": "火柴支持和钱包",
      "summary": "该功能正在等待 needs-api。",
      "needs": "needs-api",
      "lane": "server-wallet",
      "repo": "client/server/admin"
    },
    {
      "title": "火柴支持和钱包",
      "summary": "该功能正在等待 needs-review。",
      "needs": "needs-review",
      "lane": "server-wallet",
      "repo": "client/server/admin"
    },
    {
      "title": "内测管理端运营",
      "summary": "该功能正在等待 needs-server。",
      "needs": "needs-server",
      "lane": "admin-ops",
      "repo": "admin/server"
    }
  ],
  "issueTasks": [
    {
      "id": "shichai-dev/planning#6",
      "repo": "shichai-dev/planning",
      "repoName": "planning",
      "number": 6,
      "title": "[Admin Alpha] QA reduced observation console",
      "url": "https://github.com/shichai-dev/planning/issues/6",
      "state": "OPEN",
      "labels": [
        "type:handoff",
        "needs:admin",
        "needs:server",
        "needs:review",
        "ai:codex",
        "接单:待接单"
      ],
      "lane": null,
      "status": "open",
      "statusLabel": "待接单",
      "claimant": null,
      "claimedAt": null,
      "elapsedHours": null,
      "createdAt": "2026-06-17T03:36:15Z",
      "updatedAt": "2026-06-17T03:36:36Z",
      "closedAt": null,
      "parentIssue": {
        "label": "#5",
        "url": "https://github.com/shichai-dev/planning/issues/5"
      },
      "parentFeature": null,
      "totalProblem": "#5",
      "claimCommand": "/claim",
      "commandHelp": "优先在 Dashboard 面板内接单；Issue 评论命令保留为兼容兜底。系统会以 assignee 作为唯一接单锁。"
    },
    {
      "id": "shichai-dev/planning#5",
      "repo": "shichai-dev/planning",
      "repoName": "planning",
      "number": 5,
      "title": "[Feature Decision] Admin private alpha observation console",
      "url": "https://github.com/shichai-dev/planning/issues/5",
      "state": "OPEN",
      "labels": [
        "type:feature-decision",
        "type:ai-split",
        "needs:admin",
        "needs:server",
        "ai:codex",
        "接单:待接单"
      ],
      "lane": null,
      "status": "open",
      "statusLabel": "待接单",
      "claimant": null,
      "claimedAt": null,
      "elapsedHours": null,
      "createdAt": "2026-06-17T03:35:18Z",
      "updatedAt": "2026-06-17T03:36:36Z",
      "closedAt": null,
      "parentIssue": null,
      "parentFeature": null,
      "totalProblem": "未归属父问题",
      "claimCommand": "/claim",
      "commandHelp": "优先在 Dashboard 面板内接单；Issue 评论命令保留为兼容兜底。系统会以 assignee 作为唯一接单锁。"
    },
    {
      "id": "shichai-dev/opc-bounty-admin#3",
      "repo": "shichai-dev/opc-bounty-admin",
      "repoName": "opc-bounty-admin",
      "number": 3,
      "title": "[Admin Alpha] Reduce admin UI to observation console",
      "url": "https://github.com/shichai-dev/opc-bounty-admin/issues/3",
      "state": "OPEN",
      "labels": [
        "type:feature",
        "needs:api",
        "needs:admin",
        "lane:admin",
        "ai:codex",
        "接单:待接单"
      ],
      "lane": "admin",
      "status": "open",
      "statusLabel": "待接单",
      "claimant": null,
      "claimedAt": null,
      "elapsedHours": null,
      "createdAt": "2026-06-17T03:36:15Z",
      "updatedAt": "2026-06-17T03:36:36Z",
      "closedAt": null,
      "parentIssue": {
        "label": "#5",
        "url": "https://github.com/shichai-dev/planning/issues/5"
      },
      "parentFeature": null,
      "totalProblem": "#5",
      "claimCommand": "/claim",
      "commandHelp": "优先在 Dashboard 面板内接单；Issue 评论命令保留为兼容兜底。系统会以 assignee 作为唯一接单锁。"
    },
    {
      "id": "shichai-dev/opc-bounty-server#8",
      "repo": "shichai-dev/opc-bounty-server",
      "repoName": "opc-bounty-server",
      "number": 8,
      "title": "[Admin Alpha] Server minimal observation and safety APIs",
      "url": "https://github.com/shichai-dev/opc-bounty-server/issues/8",
      "state": "OPEN",
      "labels": [
        "type:feature",
        "needs:api",
        "needs:admin",
        "needs:server",
        "needs:db",
        "lane:server",
        "ai:codex",
        "接单:待接单"
      ],
      "lane": "server",
      "status": "open",
      "statusLabel": "待接单",
      "claimant": null,
      "claimedAt": null,
      "elapsedHours": null,
      "createdAt": "2026-06-17T03:36:15Z",
      "updatedAt": "2026-06-17T03:36:36Z",
      "closedAt": null,
      "parentIssue": {
        "label": "#5",
        "url": "https://github.com/shichai-dev/planning/issues/5"
      },
      "parentFeature": null,
      "totalProblem": "#5",
      "claimCommand": "/claim",
      "commandHelp": "优先在 Dashboard 面板内接单；Issue 评论命令保留为兼容兜底。系统会以 assignee 作为唯一接单锁。"
    },
    {
      "id": "shichai-dev/opc-bounty-server#7",
      "repo": "shichai-dev/opc-bounty-server",
      "repoName": "opc-bounty-server",
      "number": 7,
      "title": "[Admin Alpha] Contract minimal observation APIs",
      "url": "https://github.com/shichai-dev/opc-bounty-server/issues/7",
      "state": "OPEN",
      "labels": [
        "type:api-contract",
        "needs:api",
        "needs:admin",
        "needs:server",
        "lane:server",
        "ai:codex",
        "接单:待接单"
      ],
      "lane": "server",
      "status": "open",
      "statusLabel": "待接单",
      "claimant": null,
      "claimedAt": null,
      "elapsedHours": null,
      "createdAt": "2026-06-17T03:36:15Z",
      "updatedAt": "2026-06-17T03:36:36Z",
      "closedAt": null,
      "parentIssue": {
        "label": "#5",
        "url": "https://github.com/shichai-dev/planning/issues/5"
      },
      "parentFeature": null,
      "totalProblem": "#5",
      "claimCommand": "/claim",
      "commandHelp": "优先在 Dashboard 面板内接单；Issue 评论命令保留为兼容兜底。系统会以 assignee 作为唯一接单锁。"
    },
    {
      "id": "shichai-dev/planning#4",
      "repo": "shichai-dev/planning",
      "repoName": "planning",
      "number": 4,
      "title": "[Client Alpha] QA reduced private-alpha vertical slice",
      "url": "https://github.com/shichai-dev/planning/issues/4",
      "state": "OPEN",
      "labels": [
        "type:handoff",
        "needs:client",
        "needs:server",
        "needs:review",
        "ai:codex",
        "接单:待接单"
      ],
      "lane": null,
      "status": "open",
      "statusLabel": "待接单",
      "claimant": null,
      "claimedAt": null,
      "elapsedHours": null,
      "createdAt": "2026-06-17T02:35:03Z",
      "updatedAt": "2026-06-17T02:35:13Z",
      "closedAt": null,
      "parentIssue": {
        "label": "#3",
        "url": "https://github.com/shichai-dev/planning/issues/3"
      },
      "parentFeature": null,
      "totalProblem": "#3",
      "claimCommand": "/claim",
      "commandHelp": "优先在 Dashboard 面板内接单；Issue 评论命令保留为兼容兜底。系统会以 assignee 作为唯一接单锁。"
    },
    {
      "id": "shichai-dev/opc-bounty-client#4",
      "repo": "shichai-dev/opc-bounty-client",
      "repoName": "opc-bounty-client",
      "number": 4,
      "title": "[Client Alpha] Implement reduced private-alpha user client vertical slice",
      "url": "https://github.com/shichai-dev/opc-bounty-client/issues/4",
      "state": "OPEN",
      "labels": [
        "type:feature",
        "needs:api",
        "needs:server",
        "lane:client",
        "ai:codex",
        "接单:待接单"
      ],
      "lane": "client",
      "status": "open",
      "statusLabel": "待接单",
      "claimant": null,
      "claimedAt": null,
      "elapsedHours": null,
      "createdAt": "2026-06-17T02:35:00Z",
      "updatedAt": "2026-06-17T02:35:12Z",
      "closedAt": null,
      "parentIssue": {
        "label": "#3",
        "url": "https://github.com/shichai-dev/planning/issues/3"
      },
      "parentFeature": null,
      "totalProblem": "#3",
      "claimCommand": "/claim",
      "commandHelp": "优先在 Dashboard 面板内接单；Issue 评论命令保留为兼容兜底。系统会以 assignee 作为唯一接单锁。"
    },
    {
      "id": "shichai-dev/opc-bounty-server#5",
      "repo": "shichai-dev/opc-bounty-server",
      "repoName": "opc-bounty-server",
      "number": 5,
      "title": "[Client Alpha] Define reduced private-alpha API contract",
      "url": "https://github.com/shichai-dev/opc-bounty-server/issues/5",
      "state": "OPEN",
      "labels": [
        "type:api-contract",
        "needs:client",
        "needs:server",
        "lane:server",
        "ai:codex",
        "接单:待接单"
      ],
      "lane": "server",
      "status": "open",
      "statusLabel": "待接单",
      "claimant": null,
      "claimedAt": null,
      "elapsedHours": null,
      "createdAt": "2026-06-17T02:34:55Z",
      "updatedAt": "2026-06-17T02:35:09Z",
      "closedAt": null,
      "parentIssue": {
        "label": "#3",
        "url": "https://github.com/shichai-dev/planning/issues/3"
      },
      "parentFeature": null,
      "totalProblem": "#3",
      "claimCommand": "/claim",
      "commandHelp": "优先在 Dashboard 面板内接单；Issue 评论命令保留为兼容兜底。系统会以 assignee 作为唯一接单锁。"
    },
    {
      "id": "shichai-dev/opc-bounty-server#6",
      "repo": "shichai-dev/opc-bounty-server",
      "repoName": "opc-bounty-server",
      "number": 6,
      "title": "[Client Alpha] Implement server support for reduced private-alpha vertical slice",
      "url": "https://github.com/shichai-dev/opc-bounty-server/issues/6",
      "state": "OPEN",
      "labels": [
        "type:feature",
        "needs:client",
        "needs:db",
        "lane:server",
        "ai:codex",
        "接单:待接单"
      ],
      "lane": "server",
      "status": "open",
      "statusLabel": "待接单",
      "claimant": null,
      "claimedAt": null,
      "elapsedHours": null,
      "createdAt": "2026-06-17T02:34:57Z",
      "updatedAt": "2026-06-17T02:35:07Z",
      "closedAt": null,
      "parentIssue": {
        "label": "#3",
        "url": "https://github.com/shichai-dev/planning/issues/3"
      },
      "parentFeature": null,
      "totalProblem": "#3",
      "claimCommand": "/claim",
      "commandHelp": "优先在 Dashboard 面板内接单；Issue 评论命令保留为兼容兜底。系统会以 assignee 作为唯一接单锁。"
    },
    {
      "id": "shichai-dev/planning#3",
      "repo": "shichai-dev/planning",
      "repoName": "planning",
      "number": 3,
      "title": "[Feature Decision] Client private alpha reduced vertical slice",
      "url": "https://github.com/shichai-dev/planning/issues/3",
      "state": "OPEN",
      "labels": [
        "type:feature-decision",
        "type:ai-split",
        "needs:client",
        "needs:server",
        "ai:codex",
        "接单:待接单"
      ],
      "lane": null,
      "status": "open",
      "statusLabel": "待接单",
      "claimant": null,
      "claimedAt": null,
      "elapsedHours": null,
      "createdAt": "2026-06-17T02:32:51Z",
      "updatedAt": "2026-06-17T02:35:05Z",
      "closedAt": null,
      "parentIssue": null,
      "parentFeature": null,
      "totalProblem": "未归属父问题",
      "claimCommand": "/claim",
      "commandHelp": "优先在 Dashboard 面板内接单；Issue 评论命令保留为兼容兜底。系统会以 assignee 作为唯一接单锁。"
    },
    {
      "id": "shichai-dev/feature-dashboard#2",
      "repo": "shichai-dev/feature-dashboard",
      "repoName": "feature-dashboard",
      "number": 2,
      "title": "[评价][requirement-publishing] 首页内容太杂",
      "url": "https://github.com/shichai-dev/feature-dashboard/issues/2",
      "state": "OPEN",
      "labels": [
        "dashboard-discussion",
        "discussion:evaluation",
        "feature:requirement-publishing",
        "dispatch:sent"
      ],
      "lane": "client-publish",
      "status": "open",
      "statusLabel": "待接单",
      "claimant": null,
      "claimedAt": "2026-06-16T01:06:49.641Z",
      "elapsedHours": 884.8,
      "createdAt": "2026-06-15T16:09:26Z",
      "updatedAt": "2026-06-16T01:09:44Z",
      "closedAt": null,
      "parentIssue": null,
      "parentFeature": {
        "id": "requirement-publishing",
        "title": "需求发布流程",
        "summary": "包含材料、智能初审、追问、草稿生成、标签、保存和发布的需求发布流程。",
        "status": "implemented",
        "lane": "client-publish"
      },
      "totalProblem": "需求发布流程",
      "claimCommand": "/claim",
      "commandHelp": "优先在 Dashboard 面板内接单；Issue 评论命令保留为兼容兜底。系统会以 assignee 作为唯一接单锁。"
    },
    {
      "id": "shichai-dev/feature-dashboard#1",
      "repo": "shichai-dev/feature-dashboard",
      "repoName": "feature-dashboard",
      "number": 1,
      "title": "[修改请求][public-feature-dashboard] 仿真实平台界面异步讨论流程",
      "url": "https://github.com/shichai-dev/feature-dashboard/issues/1",
      "state": "OPEN",
      "labels": [
        "dashboard-discussion",
        "discussion:change-request",
        "status:accepted",
        "feature:public-feature-dashboard"
      ],
      "lane": "qa-release",
      "status": "open",
      "statusLabel": "待接单",
      "claimant": null,
      "claimedAt": null,
      "elapsedHours": null,
      "createdAt": "2026-06-15T12:59:40Z",
      "updatedAt": "2026-06-15T15:22:36Z",
      "closedAt": null,
      "parentIssue": null,
      "parentFeature": {
        "id": "public-feature-dashboard",
        "title": "公开异步功能讨论看板",
        "summary": "公开看板，用于展示已实现功能、未完成工作、界面页面、操作链、协作交接、异步评论和智能待处理队列。",
        "status": "in-progress",
        "lane": "qa-release"
      },
      "totalProblem": "公开异步功能讨论看板",
      "claimCommand": "/claim",
      "commandHelp": "优先在 Dashboard 面板内接单；Issue 评论命令保留为兼容兜底。系统会以 assignee 作为唯一接单锁。"
    },
    {
      "id": "shichai-dev/planning#1",
      "repo": "shichai-dev/planning",
      "repoName": "planning",
      "number": 1,
      "title": "[Feature Decision] Bootstrap shared AI collaboration workflow",
      "url": "https://github.com/shichai-dev/planning/issues/1",
      "state": "OPEN",
      "labels": [
        "type:feature-decision",
        "needs:review",
        "ai:codex"
      ],
      "lane": null,
      "status": "open",
      "statusLabel": "待接单",
      "claimant": null,
      "claimedAt": null,
      "elapsedHours": null,
      "createdAt": "2026-06-15T11:56:10Z",
      "updatedAt": "2026-06-15T11:56:10Z",
      "closedAt": null,
      "parentIssue": null,
      "parentFeature": null,
      "totalProblem": "未归属父问题",
      "claimCommand": "/claim",
      "commandHelp": "优先在 Dashboard 面板内接单；Issue 评论命令保留为兼容兜底。系统会以 assignee 作为唯一接单锁。"
    },
    {
      "id": "shichai-dev/opc-bounty-server#3",
      "repo": "shichai-dev/opc-bounty-server",
      "repoName": "opc-bounty-server",
      "number": 3,
      "title": "[QA] Verify match spending history across repos",
      "url": "https://github.com/shichai-dev/opc-bounty-server/issues/3",
      "state": "OPEN",
      "labels": [
        "type:qa",
        "needs:client",
        "needs:admin",
        "needs:server",
        "lane:qa"
      ],
      "lane": "qa",
      "status": "open",
      "statusLabel": "待接单",
      "claimant": null,
      "claimedAt": null,
      "elapsedHours": null,
      "createdAt": "2026-06-15T11:18:31Z",
      "updatedAt": "2026-06-15T11:18:31Z",
      "closedAt": null,
      "parentIssue": null,
      "parentFeature": {
        "id": "match-support-wallet",
        "title": "火柴支持和钱包",
        "summary": "测试火柴余额、项目支持、需求加赏、会员、智能额度、曝光购买和支持者讨论组。",
        "status": "implemented",
        "lane": "server-wallet"
      },
      "totalProblem": "火柴支持和钱包",
      "claimCommand": "/claim",
      "commandHelp": "优先在 Dashboard 面板内接单；Issue 评论命令保留为兼容兜底。系统会以 assignee 作为唯一接单锁。"
    },
    {
      "id": "shichai-dev/opc-bounty-admin#1",
      "repo": "shichai-dev/opc-bounty-admin",
      "repoName": "opc-bounty-admin",
      "number": 1,
      "title": "[Feature] Add match order audit filters",
      "url": "https://github.com/shichai-dev/opc-bounty-admin/issues/1",
      "state": "OPEN",
      "labels": [
        "type:feature",
        "needs:server",
        "lane:admin",
        "ai:codex"
      ],
      "lane": "admin",
      "status": "open",
      "statusLabel": "待接单",
      "claimant": null,
      "claimedAt": null,
      "elapsedHours": null,
      "createdAt": "2026-06-15T11:18:28Z",
      "updatedAt": "2026-06-15T11:18:28Z",
      "closedAt": null,
      "parentIssue": null,
      "parentFeature": {
        "id": "admin-operations",
        "title": "内测管理端运营",
        "summary": "管理端仪表盘、用户、发布内容、智能服务使用、火柴支持、内容审核、文件审核和生产就绪页面。",
        "status": "implemented",
        "lane": "admin-ops"
      },
      "totalProblem": "内测管理端运营",
      "claimCommand": "/claim",
      "commandHelp": "优先在 Dashboard 面板内接单；Issue 评论命令保留为兼容兜底。系统会以 assignee 作为唯一接单锁。"
    },
    {
      "id": "shichai-dev/opc-bounty-client#1",
      "repo": "shichai-dev/opc-bounty-client",
      "repoName": "opc-bounty-client",
      "number": 1,
      "title": "[Feature] Show user match spending history in profile",
      "url": "https://github.com/shichai-dev/opc-bounty-client/issues/1",
      "state": "OPEN",
      "labels": [
        "type:feature",
        "needs:api",
        "lane:client",
        "ai:codex"
      ],
      "lane": "client",
      "status": "open",
      "statusLabel": "待接单",
      "claimant": null,
      "claimedAt": null,
      "elapsedHours": null,
      "createdAt": "2026-06-15T11:18:25Z",
      "updatedAt": "2026-06-15T11:18:25Z",
      "closedAt": null,
      "parentIssue": null,
      "parentFeature": {
        "id": "match-support-wallet",
        "title": "火柴支持和钱包",
        "summary": "测试火柴余额、项目支持、需求加赏、会员、智能额度、曝光购买和支持者讨论组。",
        "status": "implemented",
        "lane": "server-wallet"
      },
      "totalProblem": "火柴支持和钱包",
      "claimCommand": "/claim",
      "commandHelp": "优先在 Dashboard 面板内接单；Issue 评论命令保留为兼容兜底。系统会以 assignee 作为唯一接单锁。"
    },
    {
      "id": "shichai-dev/opc-bounty-server#2",
      "repo": "shichai-dev/opc-bounty-server",
      "repoName": "opc-bounty-server",
      "number": 2,
      "title": "[DB] Match ledger query and test fixtures",
      "url": "https://github.com/shichai-dev/opc-bounty-server/issues/2",
      "state": "OPEN",
      "labels": [
        "type:db",
        "needs:server",
        "lane:database",
        "ai:codex"
      ],
      "lane": "database",
      "status": "open",
      "statusLabel": "待接单",
      "claimant": null,
      "claimedAt": null,
      "elapsedHours": null,
      "createdAt": "2026-06-15T11:18:21Z",
      "updatedAt": "2026-06-15T11:18:21Z",
      "closedAt": null,
      "parentIssue": null,
      "parentFeature": {
        "id": "match-support-wallet",
        "title": "火柴支持和钱包",
        "summary": "测试火柴余额、项目支持、需求加赏、会员、智能额度、曝光购买和支持者讨论组。",
        "status": "implemented",
        "lane": "server-wallet"
      },
      "totalProblem": "火柴支持和钱包",
      "claimCommand": "/claim",
      "commandHelp": "优先在 Dashboard 面板内接单；Issue 评论命令保留为兼容兜底。系统会以 assignee 作为唯一接单锁。"
    },
    {
      "id": "shichai-dev/opc-bounty-server#1",
      "repo": "shichai-dev/opc-bounty-server",
      "repoName": "opc-bounty-server",
      "number": 1,
      "title": "[API] User match spending history endpoint",
      "url": "https://github.com/shichai-dev/opc-bounty-server/issues/1",
      "state": "OPEN",
      "labels": [
        "type:api-contract",
        "needs:client",
        "needs:db",
        "lane:server",
        "ai:codex"
      ],
      "lane": "server",
      "status": "open",
      "statusLabel": "待接单",
      "claimant": null,
      "claimedAt": null,
      "elapsedHours": null,
      "createdAt": "2026-06-15T11:18:18Z",
      "updatedAt": "2026-06-15T11:18:18Z",
      "closedAt": null,
      "parentIssue": null,
      "parentFeature": {
        "id": "match-support-wallet",
        "title": "火柴支持和钱包",
        "summary": "测试火柴余额、项目支持、需求加赏、会员、智能额度、曝光购买和支持者讨论组。",
        "status": "implemented",
        "lane": "server-wallet"
      },
      "totalProblem": "火柴支持和钱包",
      "claimCommand": "/claim",
      "commandHelp": "优先在 Dashboard 面板内接单；Issue 评论命令保留为兼容兜底。系统会以 assignee 作为唯一接单锁。"
    },
    {
      "id": "shichai-dev/opc-bounty-client#2",
      "repo": "shichai-dev/opc-bounty-client",
      "repoName": "opc-bounty-client",
      "number": 2,
      "title": "[Dashboard分发] 需求发布流程：首页与展示台入口合并讨论",
      "url": "https://github.com/shichai-dev/opc-bounty-client/issues/2",
      "state": "OPEN",
      "labels": [
        "from:dashboard",
        "lane:client-publish",
        "接单:已接单",
        "接单:开发中"
      ],
      "lane": "client-publish",
      "status": "in-progress",
      "statusLabel": "开发中",
      "claimant": "sexymonk",
      "claimedAt": "2026-06-16T01:06:36Z",
      "elapsedHours": 884.8,
      "createdAt": "2026-06-16T00:43:58Z",
      "updatedAt": "2026-06-16T01:09:22Z",
      "closedAt": null,
      "parentIssue": null,
      "parentFeature": {
        "id": "requirement-publishing",
        "title": "需求发布流程",
        "summary": "包含材料、智能初审、追问、草稿生成、标签、保存和发布的需求发布流程。",
        "status": "implemented",
        "lane": "client-publish"
      },
      "totalProblem": "需求发布流程",
      "claimCommand": "/ready-pr 或 /handoff @用户名",
      "commandHelp": "优先在 Dashboard 面板内接单；Issue 评论命令保留为兼容兜底。系统会以 assignee 作为唯一接单锁。"
    },
    {
      "id": "shichai-dev/planning#7",
      "repo": "shichai-dev/planning",
      "repoName": "planning",
      "number": 7,
      "title": "[E2E Test][Development AI] [Test] 开发面板中台 AI 完整流程测试 - 基于 issue #6",
      "url": "https://github.com/shichai-dev/planning/issues/7",
      "state": "CLOSED",
      "labels": [
        "type:handoff",
        "ai:codex",
        "接单:待接单",
        "test",
        "e2e-test"
      ],
      "lane": null,
      "status": "closed",
      "statusLabel": "已关闭",
      "claimant": null,
      "claimedAt": "2026-06-17T12:59:32.573Z",
      "elapsedHours": 0,
      "createdAt": "2026-06-17T12:59:27Z",
      "updatedAt": "2026-06-17T12:59:56Z",
      "closedAt": "2026-06-17T12:59:51Z",
      "parentIssue": null,
      "parentFeature": null,
      "totalProblem": "未归属父问题",
      "claimCommand": "/claim",
      "commandHelp": "优先在 Dashboard 面板内接单；Issue 评论命令保留为兼容兜底。系统会以 assignee 作为唯一接单锁。"
    },
    {
      "id": "shichai-dev/opc-bounty-client#8",
      "repo": "shichai-dev/opc-bounty-client",
      "repoName": "opc-bounty-client",
      "number": 8,
      "title": "[Smoke][development-ai-middleware] deployed final issue endpoint 2026-06-17T10:12:23.835Z",
      "url": "https://github.com/shichai-dev/opc-bounty-client/issues/8",
      "state": "CLOSED",
      "labels": [
        "接单:已关闭",
        "panel:final-implementation",
        "smoke-test"
      ],
      "lane": null,
      "status": "closed",
      "statusLabel": "已关闭",
      "claimant": null,
      "claimedAt": null,
      "elapsedHours": null,
      "createdAt": "2026-06-17T10:12:25Z",
      "updatedAt": "2026-06-17T10:13:01Z",
      "closedAt": "2026-06-17T10:12:36Z",
      "parentIssue": null,
      "parentFeature": null,
      "totalProblem": "未归属父问题",
      "claimCommand": "/claim",
      "commandHelp": "优先在 Dashboard 面板内接单；Issue 评论命令保留为兼容兜底。系统会以 assignee 作为唯一接单锁。"
    },
    {
      "id": "shichai-dev/opc-bounty-client#7",
      "repo": "shichai-dev/opc-bounty-client",
      "repoName": "opc-bounty-client",
      "number": 7,
      "title": "[Idea][requirement-publishing] 发布需求: [Smoke] 发布需求按钮文案测试 2026-06-17T10:05:54.826Z",
      "url": "https://github.com/shichai-dev/opc-bounty-client/issues/7",
      "state": "CLOSED",
      "labels": [
        "from:development-panel",
        "module:client frontend",
        "topic:idea",
        "接单:已关闭"
      ],
      "lane": null,
      "status": "closed",
      "statusLabel": "已关闭",
      "claimant": null,
      "claimedAt": null,
      "elapsedHours": null,
      "createdAt": "2026-06-17T10:05:56Z",
      "updatedAt": "2026-06-17T10:06:31Z",
      "closedAt": "2026-06-17T10:06:05Z",
      "parentIssue": null,
      "parentFeature": null,
      "totalProblem": "未归属父问题",
      "claimCommand": "/claim",
      "commandHelp": "优先在 Dashboard 面板内接单；Issue 评论命令保留为兼容兜底。系统会以 assignee 作为唯一接单锁。"
    },
    {
      "id": "shichai-dev/opc-bounty-client#6",
      "repo": "shichai-dev/opc-bounty-client",
      "repoName": "opc-bounty-client",
      "number": 6,
      "title": "[Idea][requirement-publishing] 发布需求: [Smoke] 发布需求按钮文案测试 2026-06-17T10:03:38.774Z",
      "url": "https://github.com/shichai-dev/opc-bounty-client/issues/6",
      "state": "CLOSED",
      "labels": [
        "from:development-panel",
        "module:client frontend",
        "topic:idea",
        "接单:已关闭"
      ],
      "lane": null,
      "status": "closed",
      "statusLabel": "已关闭",
      "claimant": null,
      "claimedAt": null,
      "elapsedHours": null,
      "createdAt": "2026-06-17T10:03:40Z",
      "updatedAt": "2026-06-17T10:05:47Z",
      "closedAt": "2026-06-17T10:05:20Z",
      "parentIssue": null,
      "parentFeature": null,
      "totalProblem": "未归属父问题",
      "claimCommand": "/claim",
      "commandHelp": "优先在 Dashboard 面板内接单；Issue 评论命令保留为兼容兜底。系统会以 assignee 作为唯一接单锁。"
    },
    {
      "id": "shichai-dev/opc-bounty-client#5",
      "repo": "shichai-dev/opc-bounty-client",
      "repoName": "opc-bounty-client",
      "number": 5,
      "title": "[Idea][requirement-publishing] 发布需求: [Smoke] 发布需求按钮文案测试 2026-06-17T10:01:54.396Z",
      "url": "https://github.com/shichai-dev/opc-bounty-client/issues/5",
      "state": "CLOSED",
      "labels": [
        "from:development-panel",
        "module:client frontend",
        "topic:idea",
        "接单:已关闭"
      ],
      "lane": null,
      "status": "closed",
      "statusLabel": "已关闭",
      "claimant": null,
      "claimedAt": null,
      "elapsedHours": null,
      "createdAt": "2026-06-17T10:01:58Z",
      "updatedAt": "2026-06-17T10:05:43Z",
      "closedAt": "2026-06-17T10:05:20Z",
      "parentIssue": null,
      "parentFeature": null,
      "totalProblem": "未归属父问题",
      "claimCommand": "/claim",
      "commandHelp": "优先在 Dashboard 面板内接单；Issue 评论命令保留为兼容兜底。系统会以 assignee 作为唯一接单锁。"
    },
    {
      "id": "shichai-dev/feature-dashboard#8",
      "repo": "shichai-dev/feature-dashboard",
      "repoName": "feature-dashboard",
      "number": 8,
      "title": "[Smoke][development-ai-middleware] Final issue endpoint 2026-06-17T09:07:14.540Z",
      "url": "https://github.com/shichai-dev/feature-dashboard/issues/8",
      "state": "CLOSED",
      "labels": [
        "from:development-panel",
        "topic:smoke",
        "接单:已关闭"
      ],
      "lane": null,
      "status": "closed",
      "statusLabel": "已关闭",
      "claimant": null,
      "claimedAt": null,
      "elapsedHours": null,
      "createdAt": "2026-06-17T09:07:16Z",
      "updatedAt": "2026-06-17T09:07:43Z",
      "closedAt": "2026-06-17T09:07:27Z",
      "parentIssue": null,
      "parentFeature": null,
      "totalProblem": "未归属父问题",
      "claimCommand": "/claim",
      "commandHelp": "优先在 Dashboard 面板内接单；Issue 评论命令保留为兼容兜底。系统会以 assignee 作为唯一接单锁。"
    }
  ],
  "discussions": [
    {
      "id": "dashboard-2",
      "number": 2,
      "title": "[评价][requirement-publishing] 首页内容太杂",
      "url": "https://github.com/shichai-dev/feature-dashboard/issues/2",
      "state": "OPEN",
      "featureId": "requirement-publishing",
      "uiSurface": "用户端首页",
      "operationStepId": "publish-requirement-start",
      "hotspotId": "home-publish-requirement",
      "type": "evaluation",
      "lifecycle": "stale",
      "needsAiReview": false,
      "commentCount": 6,
      "labels": [
        "dashboard-discussion",
        "discussion:evaluation",
        "feature:requirement-publishing",
        "dispatch:sent"
      ],
      "dispatch": {
        "status": "sent",
        "statusLabel": "已分发",
        "targetUrl": "https://github.com/shichai-dev/opc-bounty-client/issues/2",
        "targetRepo": "shichai-dev/opc-bounty-client"
      },
      "createdAt": "2026-06-15T16:09:26Z",
      "updatedAt": "2026-06-16T01:09:44Z",
      "closedAt": null,
      "preview": "功能编号: requirement-publishing 功能: 需求发布流程 界面页面: 用户端首页 操作步骤: publish-requirement-start 热点编号: home-publish-requirement 讨论类型: evaluation 选中的界面: - 页面: 首页 - 操作点: 发布需求 - 当前行为: 智能助手整理成合作..."
    },
    {
      "id": "dashboard-1",
      "number": 1,
      "title": "[修改请求][public-feature-dashboard] 仿真实平台界面异步讨论流程",
      "url": "https://github.com/shichai-dev/feature-dashboard/issues/1",
      "state": "OPEN",
      "featureId": "public-feature-dashboard",
      "uiSurface": "- 公开功能讨论看板（feature-dashboard /）",
      "operationStepId": null,
      "hotspotId": null,
      "type": "change-request",
      "lifecycle": "accepted",
      "needsAiReview": false,
      "commentCount": 1,
      "labels": [
        "dashboard-discussion",
        "discussion:change-request",
        "status:accepted",
        "feature:public-feature-dashboard"
      ],
      "dispatch": {
        "status": "untracked",
        "statusLabel": "未进入分发",
        "targetUrl": null,
        "targetRepo": null
      },
      "createdAt": "2026-06-15T12:59:40Z",
      "updatedAt": "2026-06-15T15:22:36Z",
      "closedAt": null,
      "preview": "功能编号: public-feature-dashboard 功能: 公开异步功能讨论看板 讨论类型: 修改请求 目标界面页面: - 公开功能讨论看板（feature-dashboard /） 建议或评价: 这个看板不应该只是只读状态页。团队成员需要能从看板里直接输入新功能想法、评价已经实现的功能，并在仿真实平台界面上围绕按钮、图标、页面区域和操作链进..."
    }
  ],
  "aiReviewQueue": [
    {
      "type": "handoff",
      "title": "火柴支持和钱包",
      "featureId": "match-support-wallet",
      "reason": "needs-db",
      "repo": "client/server/admin",
      "lane": "server-wallet"
    },
    {
      "type": "handoff",
      "title": "火柴支持和钱包",
      "featureId": "match-support-wallet",
      "reason": "needs-server",
      "repo": "client/server/admin",
      "lane": "server-wallet"
    },
    {
      "type": "handoff",
      "title": "火柴支持和钱包",
      "featureId": "match-support-wallet",
      "reason": "needs-api",
      "repo": "client/server/admin",
      "lane": "server-wallet"
    },
    {
      "type": "handoff",
      "title": "火柴支持和钱包",
      "featureId": "match-support-wallet",
      "reason": "needs-review",
      "repo": "client/server/admin",
      "lane": "server-wallet"
    },
    {
      "type": "handoff",
      "title": "内测管理端运营",
      "featureId": "admin-operations",
      "reason": "needs-server",
      "repo": "admin/server",
      "lane": "admin-ops"
    }
  ]
}
